{
  "country": "cn",
  "appId": "481623196",
  "appInfo": {
    "trackId": 481623196,
    "country": "cn",
    "trackName": "腾讯地图-路线规划,导航打车出行",
    "trackNameShort": "腾讯地图",
    "sellerName": "Shenzhen Tencent Computer Systems Company Limited",
    "artistName": "Tencent Mobile Games",
    "artworkUrl100": "https://is2-ssl.mzstatic.com/image/thumb/Purple112/v4/7f/e6/24/7fe624f0-0a16-62bd-5f23-06d12b07a2ba/AppIcon-0-0-1x_U007emarketing-0-0-0-10-0-0-P3-0-0-0-GLES2_U002c0-512MB-85-220-0-0.png/100x100bb.jpg",
    "artworkUrl512": "https://is2-ssl.mzstatic.com/image/thumb/Purple112/v4/7f/e6/24/7fe624f0-0a16-62bd-5f23-06d12b07a2ba/AppIcon-0-0-1x_U007emarketing-0-0-0-10-0-0-P3-0-0-0-GLES2_U002c0-512MB-85-220-0-0.png/512x512bb.jpg"
  },
  "appVersion": [
    {
      "id": 31971655,
      "country": "cn",
      "trackId": 481623196,
      "versionId": "847907710",
      "versionName": "9.21.2",
      "versionDate": "2022-03-26T03:12:46.000Z",
      "versionDescription": "腾讯地图全新 V9.21.2 版本重磅更新，更多功能抢先体验！\n【美食优惠上线】我们上线美食优惠啦！团购、折扣买单、代金券一站搞定！\n【足迹地图升级】快来点亮你的足迹城市，解锁城市成就！",
      "createTime": "2022-04-17T15:13:12.283Z",
      "updateTime": "2022-04-17T15:13:12.283Z",
      "_hasReleaseinfo": true,
      "_isExpand": false
    },
    {
      "id": 31971656,
      "country": "cn",
      "trackId": 481623196,
      "versionId": "847792957",
      "versionName": "9.21.1",
      "versionDate": "2022-03-22T23:55:06.000Z",
      "versionDescription": "腾讯地图全新 V9.21.1 版本重磅更新，更多功能抢先体验！\n【美食优惠上线】我们上线美食优惠啦！团购、折扣买单、代金券一站搞定！\n【足迹地图升级】快来点亮你的足迹城市，解锁城市成就！",
      "createTime": "2022-04-17T15:13:12.283Z",
      "updateTime": "2022-04-17T15:13:12.283Z",
      "_hasReleaseinfo": true,
      "_isExpand": false
    },
    {
      "id": 31971657,
      "country": "cn",
      "trackId": 481623196,
      "versionId": "847655235",
      "versionName": "9.21.0",
      "versionDate": "2022-03-16T22:46:58.000Z",
      "versionDescription": "腾讯地图全新 V9.21.0 版本重磅更新，更多功能抢先体验！\n【美食优惠上线】我们上线美食优惠啦！团购、折扣买单、代金券一站搞定！\n【足迹地图升级】快来点亮你的足迹城市，解锁城市成就！",
      "createTime": "2022-04-17T15:13:12.283Z",
      "updateTime": "2022-04-17T15:13:12.283Z",
      "_hasReleaseinfo": true,
      "_isExpand": false
    },
    {
      "id": 31971658,
      "country": "cn",
      "trackId": 481623196,
      "versionId": "847166229",
      "versionName": "9.19.0",
      "versionDate": "2022-03-04T09:00:12.000Z",
      "versionDescription": "腾讯地图全新 V9.19.0 版本重磅更新，更多功能抢先体验！\n【足迹地图上线】万众期待的足迹地图功能终于上线啦！快来点亮你的足迹城市，解锁城市得成就吧！\n【终点停车推荐】目的地智能停车推荐，出行安心到达",
      "createTime": "2022-04-17T15:13:12.283Z",
      "updateTime": "2022-04-17T15:13:12.283Z",
      "_hasReleaseinfo": true,
      "_isExpand": false
    },
    {
      "id": 31971659,
      "country": "cn",
      "trackId": 481623196,
      "versionId": "845469429",
      "versionName": "9.18.0",
      "versionDate": "2022-02-09T02:36:10.000Z",
      "versionDescription": "腾讯地图全新 V9.18.0 版本重磅更新，更多功能抢先体验！\r\n【绿色出行模块上线】 更丰富的公共出行路线规划，低碳生活，绿色相伴~\r\n【王者荣耀主题升级】 主题氛围感up，快来打造你的专属导航体验！\r",
      "createTime": "2022-04-17T15:13:12.283Z",
      "updateTime": "2022-04-17T15:13:12.283Z",
      "_hasReleaseinfo": true,
      "_isExpand": false
    },
    {
      "id": 31971660,
      "country": "cn",
      "trackId": 481623196,
      "versionId": "845281316",
      "versionName": "9.17.1",
      "versionDate": "2021-11-18T00:24:22.000Z",
      "versionDescription": "腾讯地图全新 V9.17.1 版本重磅更新，更多功能抢先体验！\n【主题广场升级改版】使用主题车标时，可以一键选择同款语音包啦，更多有趣主题等你发掘\n【新增红灯等待次数】拥堵信息更详细，开车等灯不焦虑\n【新增多人被拍提示】违章高发位置强化提醒，安全驾驶遵守交规",
      "createTime": "2022-04-17T15:13:12.283Z",
      "updateTime": "2022-04-17T15:13:12.283Z",
      "_hasReleaseinfo": true,
      "_isExpand": false
    },
    {
      "id": 31971661,
      "country": "cn",
      "trackId": 481623196,
      "versionId": "845231065",
      "versionName": "9.17.0",
      "versionDate": "2021-11-11T03:34:45.000Z",
      "versionDescription": "腾讯地图全新 V9.17.0 版本重磅更新，更多功能抢先体验！\n【主题广场升级改版】使用主题车标时，可以一键选择同款语音包啦，更多有趣主题等你发掘\n【新增红灯等待次数】拥堵信息更详细，开车等灯不焦虑\n【新增多人被拍提示】违章高发位置强化提醒，安全驾驶遵守交规",
      "createTime": "2022-04-17T15:13:12.283Z",
      "updateTime": "2022-04-17T15:13:12.283Z",
      "_hasReleaseinfo": true,
      "_isExpand": false
    },
    {
      "id": 31971662,
      "country": "cn",
      "trackId": 481623196,
      "versionId": "844934969",
      "versionName": "9.16.2",
      "versionDate": "2021-10-29T02:40:39.000Z",
      "versionDescription": "腾讯地图全新 V9.16.2 版本重磅更新，伴你十一玩出趣！\n【首页焕新】首页视觉升级，全新亮相，十一伴你趣出行。\n【明星语音】杨幂、黄渤齐上新，一键下载，十一出游明星伴你行。\n【榜单推荐】吃喝玩乐最全推荐，看攻略刷视频，十一去哪儿不用愁。\n【打车升级】打车焕新颜，多种车型随心选，十一打车就是快。\n即刻更新，体验新版本。",
      "createTime": "2022-04-17T15:13:12.283Z",
      "updateTime": "2022-04-17T15:13:12.283Z",
      "_hasReleaseinfo": true,
      "_isExpand": false
    },
    {
      "id": 31971663,
      "country": "cn",
      "trackId": 481623196,
      "versionId": "844597461",
      "versionName": "9.16.1",
      "versionDate": "2021-10-13T00:16:49.000Z",
      "versionDescription": "腾讯地图全新 V9.16.1 版本重磅更新，伴你十一玩出趣！\n【首页焕新】首页视觉升级，全新亮相，十一伴你趣出行。\n【明星语音】杨幂、黄渤齐上新，一键下载，十一出游明星伴你行。\n【榜单推荐】吃喝玩乐最全推荐，看攻略刷视频，十一去哪儿不用愁。\n【打车升级】打车焕新颜，多种车型随心选，十一打车就是快。\n即刻更新，体验新版本。",
      "createTime": "2022-04-17T15:13:12.283Z",
      "updateTime": "2022-04-17T15:13:12.283Z",
      "_hasReleaseinfo": true,
      "_isExpand": false
    },
    {
      "id": 31971664,
      "country": "cn",
      "trackId": 481623196,
      "versionId": "844244630",
      "versionName": "9.16.0",
      "versionDate": "2021-09-30T07:49:16.000Z",
      "versionDescription": "腾讯地图全新 V9.16.0 版本重磅更新，伴你十一玩出趣！\n【首页焕新】首页视觉升级，全新亮相，十一伴你趣出行。\n【明星语音】杨幂、黄渤齐上新，一键下载，十一出游明星伴你行。\n【榜单推荐】吃喝玩乐最全推荐，看攻略刷视频，十一去哪儿不用愁。\n【打车升级】打车焕新颜，多种车型随心选，十一打车就是快。\n即刻更新，体验新版本。",
      "createTime": "2022-04-17T15:13:12.283Z",
      "updateTime": "2022-04-17T15:13:12.283Z",
      "_hasReleaseinfo": true,
      "_isExpand": false
    },
    {
      "id": 31971665,
      "country": "cn",
      "trackId": 481623196,
      "versionId": "843977673",
      "versionName": "9.15.1",
      "versionDate": "2021-09-08T02:09:04.000Z",
      "versionDescription": "腾讯地图V9.15.1全新发布，新增功能抢先体验：\n【明星导航语音上线】语音广场下载明星语音包，一键分享乐趣加倍。\n【支持添加车辆通行证】智能路线规划避免限行罚款，驾车出行更加高效畅通。\n即刻更新，体验新版本。",
      "createTime": "2022-04-17T15:13:12.283Z",
      "updateTime": "2022-04-17T15:13:12.283Z",
      "_hasReleaseinfo": true,
      "_isExpand": false
    },
    {
      "id": 31971666,
      "country": "cn",
      "trackId": 481623196,
      "versionId": "843856222",
      "versionName": "9.15.0",
      "versionDate": "2021-09-01T01:38:01.000Z",
      "versionDescription": "腾讯地图V9.15.0全新发布，新增功能抢先体验：\n【明星导航语音上线】语音广场下载明星语音包，一键分享乐趣加倍。\n【支持添加车辆通行证】智能路线规划避免限行罚款，驾车出行更加高效畅通。\n即刻更新，体验新版本。",
      "createTime": "2022-04-17T15:13:12.283Z",
      "updateTime": "2022-04-17T15:13:12.283Z",
      "_hasReleaseinfo": true,
      "_isExpand": false
    },
    {
      "id": 31971667,
      "country": "cn",
      "trackId": 481623196,
      "versionId": "843433900",
      "versionName": "9.14.0",
      "versionDate": "2021-08-08T03:50:53.000Z",
      "versionDescription": "腾讯地图V9.14.0全新发布，新增功能抢先体验：\n【特色导航语音支持分享】沉浸试听如临其境，一键分享乐趣加倍。\n【支持添加车辆通行证】智能路线规划避免限行罚款，驾车出行更加高效畅通。\n即刻更新，体验新版本。",
      "createTime": "2022-04-17T15:13:12.283Z",
      "updateTime": "2022-04-17T15:13:12.283Z",
      "_hasReleaseinfo": true,
      "_isExpand": false
    },
    {
      "id": 31971668,
      "country": "cn",
      "trackId": 481623196,
      "versionId": "843197397",
      "versionName": "9.13.0",
      "versionDate": "2021-07-27T02:54:16.000Z",
      "versionDescription": "腾讯地图V9.13.0全新发布，出行路线选择更多样，伴你暑期安全出游！\n【避开禁行交规提示】禁行交规早提醒，提前避开不违章\n【积水地图】提前查看道路积水点，夏天雨季安全出行\n即刻更新，体验新版本。",
      "createTime": "2022-04-17T15:13:12.283Z",
      "updateTime": "2022-04-17T15:13:12.283Z",
      "_hasReleaseinfo": true,
      "_isExpand": false
    },
    {
      "id": 31971669,
      "country": "cn",
      "trackId": 481623196,
      "versionId": "842772344",
      "versionName": "9.12.0",
      "versionDate": "2021-06-25T02:19:01.000Z",
      "versionDescription": "腾讯地图V9.12.0全新发布，出行路线选择更多样，伴你暑期轻松出游！\n【路线偏好上新】新增大路优先、时间最短两种路线偏好，丰富你的出行选择。\n【步骑行路线解释全面上线】显示绿色出行专用通道，路面情况解释更详细。\n【城市详情页再升级】城市交通、旅游信息、热门榜单、酒店推荐一应俱全。\n即刻更新，体验新版本。",
      "createTime": "2022-04-17T15:13:12.283Z",
      "updateTime": "2022-04-17T15:13:12.283Z",
      "_hasReleaseinfo": true,
      "_isExpand": false
    },
    {
      "id": 31971670,
      "country": "cn",
      "trackId": 481623196,
      "versionId": "842517314",
      "versionName": "9.11.1",
      "versionDate": "2021-06-08T05:38:35.000Z",
      "versionDescription": "腾讯地图V9.11.1全新发布，跨城出行功能再升级，伴你端午轻松出游！\n【未来限行提示】提前避开限行，放心驾驶不违章。\n【跨城火车、客车查询】一键购票轻松付，行程提醒超贴心。\n【火车行程动态提醒】进出站信息一手掌握，行程提醒随时看。\n【一键下载离线地图】长途出行导航，一键下载途经城市离线地图。\n即刻更新，体验新版本。",
      "createTime": "2022-04-17T15:13:12.283Z",
      "updateTime": "2022-04-17T15:13:12.283Z",
      "_hasReleaseinfo": true,
      "_isExpand": false
    },
    {
      "id": 31971671,
      "country": "cn",
      "trackId": 481623196,
      "versionId": "842485822",
      "versionName": "9.11.0",
      "versionDate": "2021-06-04T02:40:44.000Z",
      "versionDescription": "腾讯地图V9.11.0全新发布，跨城出行功能再升级，伴你端午轻松出游！\n【未来限行提示】提前避开限行，放心驾驶不违章。\n【跨城火车、客车查询】一键购票轻松付，行程提醒超贴心。\n【火车行程动态提醒】进出站信息一手掌握，行程提醒随时看。\n【一键下载离线地图】长途出行导航，一键下载途经城市离线地图。\n即刻更新，体验新版本。",
      "createTime": "2022-04-17T15:13:12.283Z",
      "updateTime": "2022-04-17T15:13:12.283Z",
      "_hasReleaseinfo": true,
      "_isExpand": false
    },
    {
      "id": 31971672,
      "country": "cn",
      "trackId": 481623196,
      "versionId": "842193636",
      "versionName": "9.10.1",
      "versionDate": "2021-05-18T03:12:05.000Z",
      "versionDescription": "腾讯地图V9.10.1全新发布，新增功能抢先体验：\n【跨城火车、客车查询】一键购票轻松付，行程提醒超贴心。\n【火车行程动态提醒】进出站信息一手掌握，行程提醒随时看。\n即刻更新，体验新版本。",
      "createTime": "2022-04-17T15:13:12.283Z",
      "updateTime": "2022-04-17T15:13:12.283Z",
      "_hasReleaseinfo": true,
      "_isExpand": false
    },
    {
      "id": 31971673,
      "country": "cn",
      "trackId": 481623196,
      "versionId": "842139220",
      "versionName": "9.10.0",
      "versionDate": "2021-05-12T02:47:31.000Z",
      "versionDescription": "腾讯地图V9.10.0全新发布，新增功能抢先体验：\n【跨城火车、客车查询】一键购票轻松付，行程提醒超贴心。\n【火车行程动态提醒】进出站信息一手掌握，行程提醒随时看。\n即刻更新，体验新版本。",
      "createTime": "2022-04-17T15:13:12.283Z",
      "updateTime": "2022-04-17T15:13:12.283Z",
      "_hasReleaseinfo": true,
      "_isExpand": false
    },
    {
      "id": 31971674,
      "country": "cn",
      "trackId": 481623196,
      "versionId": "841914595",
      "versionName": "9.9.3",
      "versionDate": "2021-04-27T03:58:09.000Z",
      "versionDescription": "腾讯地图V9.9.3全新发布，新增功能抢先体验：\n【叮当支持点播音乐】导航中点播歌曲，唤醒叮当来搞定。\n【附近实时公交推荐】多条线路实时到站提示，出行乘车更便捷。\n即刻更新，体验新版本。",
      "createTime": "2022-04-17T15:13:12.283Z",
      "updateTime": "2022-04-17T15:13:12.283Z",
      "_hasReleaseinfo": true,
      "_isExpand": false
    },
    {
      "id": 31971675,
      "country": "cn",
      "trackId": 481623196,
      "versionId": "841628092",
      "versionName": "9.9.2",
      "versionDate": "2021-04-22T01:05:06.000Z",
      "versionDescription": "腾讯地图V9.9.2全新发布，新增功能抢先体验：\n【叮当支持点播音乐】导航中点播歌曲，唤醒叮当来搞定。\n【附近实时公交推荐】多条线路实时到站提示，出行乘车更便捷。\n即刻更新，体验新版本。",
      "createTime": "2022-04-17T15:13:12.283Z",
      "updateTime": "2022-04-17T15:13:12.283Z",
      "_hasReleaseinfo": true,
      "_isExpand": false
    },
    {
      "id": 31971676,
      "country": "cn",
      "trackId": 481623196,
      "versionId": "841400018",
      "versionName": "9.9.1",
      "versionDate": "2021-04-18T16:39:30.000Z",
      "versionDescription": "腾讯地图V9.9.1全新发布，新增功能抢先体验：\n【叮当支持点播音乐】导航中点播歌曲，唤醒叮当来搞定。\n【附近实时公交推荐】多条线路实时到站提示，出行乘车更便捷。\n即刻更新，体验新版本。",
      "createTime": "2022-04-17T15:13:12.283Z",
      "updateTime": "2022-04-17T15:13:12.283Z",
      "_hasReleaseinfo": true,
      "_isExpand": false
    },
    {
      "id": 31971677,
      "country": "cn",
      "trackId": 481623196,
      "versionId": "841315533",
      "versionName": "9.9.0",
      "versionDate": "2021-04-15T07:07:33.000Z",
      "versionDescription": "腾讯地图V9.9.0全新发布，新增功能抢先体验：\n【叮当支持点播音乐】导航中点播歌曲，唤醒叮当来搞定。\n【附近实时公交推荐】多条线路实时到站提示，出行乘车更便捷。\n即刻更新，体验新版本。",
      "createTime": "2022-04-17T15:13:12.283Z",
      "updateTime": "2022-04-17T15:13:12.283Z",
      "_hasReleaseinfo": true,
      "_isExpand": false
    },
    {
      "id": 31971678,
      "country": "cn",
      "trackId": 481623196,
      "versionId": "841003136",
      "versionName": "9.8.0",
      "versionDate": "2021-03-25T04:00:33.000Z",
      "versionDescription": "腾讯地图V9.8.0全新发布，踏春正当时，新增功能抢先体验：\n【首页搜索框位置自定义】搜索框上下随心选，单手操作更简便。\n【驾车路线未来用时上线】大数据预估路线用时，决策出发时间更方便。\n【拥堵趋势预测】交通路况提前预知，早知早到目的地。\n即刻更新，体验新版本。",
      "createTime": "2022-04-17T15:13:12.283Z",
      "updateTime": "2022-04-17T15:13:12.283Z",
      "_hasReleaseinfo": true,
      "_isExpand": false
    },
    {
      "id": 31971679,
      "country": "cn",
      "trackId": 481623196,
      "versionId": "840592695",
      "versionName": "9.7.0",
      "versionDate": "2021-02-25T06:07:51.000Z",
      "versionDescription": "腾讯地图V9.7.0全新发布。踏春正当时，新增功能抢先体验：\n【导航新增3D建筑显示】地图显示更精细，导航视觉新体验。\n【出行服务全面覆盖】更多服务尽在工具栏，叮当一喊轻松唤起。\n【实时公交卡片样式升级】多辆公交到站信息显示，出行乘车更便捷。\n即刻更新，体验新版本。",
      "createTime": "2022-04-17T15:13:12.283Z",
      "updateTime": "2022-04-17T15:13:12.283Z",
      "_hasReleaseinfo": true,
      "_isExpand": false
    },
    {
      "id": 31971680,
      "country": "cn",
      "trackId": 481623196,
      "versionId": "840155284",
      "versionName": "9.6.0",
      "versionDate": "2021-02-04T03:19:01.000Z",
      "versionDescription": "春节专版V9.6.0发布，新增功能抢先体验：\n【CarPlay新升级】CarPlay支持分屏模式，一键投屏车载导航。\n【一键下载离线地图】一键下载途经城市离线地图，省流量更省心。\n【沿途搜更新ETA】新春出行沿途搜，预计用时更精准。\n即刻更新，体验新版本。",
      "createTime": "2022-04-17T15:13:12.283Z",
      "updateTime": "2022-04-17T15:13:12.283Z",
      "_hasReleaseinfo": true,
      "_isExpand": false
    },
    {
      "id": 31971681,
      "country": "cn",
      "trackId": 481623196,
      "versionId": "840053006",
      "versionName": "9.5.1",
      "versionDate": "2021-01-19T02:44:14.000Z",
      "versionDescription": "腾讯地图V9.5.1全新发布，新增功能抢先体验：\n【多种车型同时呼叫】极速叫车应答快，多种车型任你选。\n【QQ音乐伴你行】路线探测模式支持QQ音乐，通勤路上不无聊。\n【CarPlay新升级】CarPlay支持分屏模式，一键投屏车载导航。\n【3D车标齐上新】新车标迎新年，多种皮肤任你换。\n即刻更新，体验新版本～",
      "createTime": "2022-04-17T15:13:12.283Z",
      "updateTime": "2022-04-17T15:13:12.283Z",
      "_hasReleaseinfo": true,
      "_isExpand": false
    },
    {
      "id": 31971682,
      "country": "cn",
      "trackId": 481623196,
      "versionId": "839905185",
      "versionName": "9.5.0",
      "versionDate": "2021-01-12T02:06:42.000Z",
      "versionDescription": "腾讯地图V9.5.0全新发布，新增功能抢先体验：\n【多种车型同时呼叫】极速叫车应答快，多种车型任你选。\n【QQ音乐伴你行】路线探测模式支持QQ音乐，通勤路上不无聊。\n【CarPlay新升级】CarPlay支持分屏模式，一键投屏车载导航。\n【3D车标齐上新】新车标迎新年，多种皮肤任你换。\n即刻更新，体验新版本～",
      "createTime": "2022-04-17T15:13:12.283Z",
      "updateTime": "2022-04-17T15:13:12.283Z",
      "_hasReleaseinfo": true,
      "_isExpand": false
    },
    {
      "id": 31971683,
      "country": "cn",
      "trackId": 481623196,
      "versionId": "839643651",
      "versionName": "9.4.0",
      "versionDate": "2020-12-18T02:42:36.000Z",
      "versionDescription": "腾讯地图V9.4.0全新发布，新增功能抢先体验：\n【一键体验“极速叫车”】车型选择更多样，极速出发不等待。\n【AR步行导航】全实景路线，找位置不再难。\n【路线探测全面升级】路线路况一目了然，电子眼距离智能提醒。\n【行中增加途经点】行中多类设施支持点击，方便添加途径点。\n即刻更新，体验新版本～",
      "createTime": "2022-04-17T15:13:12.283Z",
      "updateTime": "2022-04-17T15:13:12.283Z",
      "_hasReleaseinfo": true,
      "_isExpand": false
    },
    {
      "id": 31971684,
      "country": "cn",
      "trackId": 481623196,
      "versionId": "839443781",
      "versionName": "9.3.1",
      "versionDate": "2020-12-07T04:20:07.000Z",
      "versionDescription": "腾讯地图新版本全新升级，新增功能抢先体验：\n【行中增加途经点】途中多类设施支持点击，方便添加途径点\n【连续路口大图】路口放大图体验升级，连续路口引导更贴心\n即刻更新，体验新版本～",
      "createTime": "2022-04-17T15:13:12.283Z",
      "updateTime": "2022-04-17T15:13:12.283Z",
      "_hasReleaseinfo": true,
      "_isExpand": false
    },
    {
      "id": 31971685,
      "country": "cn",
      "trackId": 481623196,
      "versionId": "839327934",
      "versionName": "9.3.0",
      "versionDate": "2020-11-30T00:27:42.000Z",
      "versionDescription": "腾讯地图新版本全新升级，新增功能抢先体验：\n【行中增加途经点】途中多类设施支持点击，方便添加途径点\n【连续路口大图】路口放大图体验升级，连续路口引导更贴心\n即刻更新，体验新版本～",
      "createTime": "2022-04-17T15:13:12.283Z",
      "updateTime": "2022-04-17T15:13:12.283Z",
      "_hasReleaseinfo": true,
      "_isExpand": false
    },
    {
      "id": 31971686,
      "country": "cn",
      "trackId": 481623196,
      "versionId": "839216483",
      "versionName": "9.2.1",
      "versionDate": "2020-11-18T00:36:25.000Z",
      "versionDescription": "腾讯地图新版本全新升级，新增功能立即体验：\n【导航轨迹回放】炫酷导航轨迹 留住出行回忆\n【一键体验“极速叫车”】叫车应答快 出发不等待\n即刻更新，体验新版本～",
      "createTime": "2022-04-17T15:13:12.283Z",
      "updateTime": "2022-04-17T15:13:12.283Z",
      "_hasReleaseinfo": true,
      "_isExpand": false
    },
    {
      "id": 31971687,
      "country": "cn",
      "trackId": 481623196,
      "versionId": "838416025",
      "versionName": "9.2.0",
      "versionDate": "2020-11-13T01:33:24.000Z",
      "versionDescription": "腾讯地图新版本全新升级，新增功能立即体验：\r\n【导航轨迹回放】炫酷导航轨迹 留住出行回忆\r\n【一键体验“极速叫车”】叫车应答快 出发不等待\r\n即刻更新，体验新版本～",
      "createTime": "2022-04-17T15:13:12.283Z",
      "updateTime": "2022-04-17T15:13:12.283Z",
      "_hasReleaseinfo": true,
      "_isExpand": false
    },
    {
      "id": 31971688,
      "country": "cn",
      "trackId": 481623196,
      "versionId": "838328952",
      "versionName": "9.1.2",
      "versionDate": "2020-10-27T01:13:29.000Z",
      "versionDescription": "【上线聚合打车服务】叫车应答快，出发不等待\r\n【业界首创整合QQ音乐】QQ音乐来入驻，导航听歌两不误",
      "createTime": "2022-04-17T15:13:12.283Z",
      "updateTime": "2022-04-17T15:13:12.283Z",
      "_hasReleaseinfo": true,
      "_isExpand": false
    },
    {
      "id": 31971689,
      "country": "cn",
      "trackId": 481623196,
      "versionId": "838218914",
      "versionName": "9.1.1",
      "versionDate": "2020-10-22T01:29:40.000Z",
      "versionDescription": "【上线聚合打车服务】叫车应答快，出发不等待\r\n【业界首创整合QQ音乐】QQ音乐来入驻，导航听歌两不误",
      "createTime": "2022-04-17T15:13:12.283Z",
      "updateTime": "2022-04-17T15:13:12.283Z",
      "_hasReleaseinfo": true,
      "_isExpand": false
    },
    {
      "id": 31971690,
      "country": "cn",
      "trackId": 481623196,
      "versionId": "838170077",
      "versionName": "9.1.0",
      "versionDate": "2020-10-15T00:29:58.000Z",
      "versionDescription": "【上线聚合打车服务】叫车应答快，出发不等待\r\n【业界首创整合QQ音乐】QQ音乐来入驻，导航听歌两不误",
      "createTime": "2022-04-17T15:13:12.283Z",
      "updateTime": "2022-04-17T15:13:12.283Z",
      "_hasReleaseinfo": true,
      "_isExpand": false
    },
    {
      "id": 31971691,
      "country": "cn",
      "trackId": 481623196,
      "versionId": "837990368",
      "versionName": "9.0.2",
      "versionDate": "2020-09-29T01:35:35.000Z",
      "versionDescription": "腾讯地图国庆专版新鲜出炉，十一轻松出游。\r\n【新首页，更懂你】智能首页全新升级，丰富工具助你出行，更懂你的出行习惯\r\n【业界首创整合QQ音乐】十一路上不无聊，用品质导航，听品质音乐，导航听歌两不误\r\n【附近、消息升级】假期去哪儿不用愁，海量出行资讯全掌握，吃喝玩乐最全推荐\r\n【路口放大图新升级】国庆驾车长途出游，不怕错过高速出口，精准抵达目的地\r\n【终点引导精细化】车站机场不迷路，出发到达更精准，少走冤枉路，助你快人一步\r\n【智能语音助手】长途出行解放双手，全语音操控更智能，叮当一下，开启AI出行\r\n【性能升级】操作体验更流畅，导航界面更清晰，文字按钮一目了然\r\n国庆佳节到，腾讯地图祝大家节日快乐！最新版本全新功能，期待体验！",
      "createTime": "2022-04-17T15:13:12.283Z",
      "updateTime": "2022-04-17T15:13:12.283Z",
      "_hasReleaseinfo": true,
      "_isExpand": false
    },
    {
      "id": 31971692,
      "country": "cn",
      "trackId": 481623196,
      "versionId": "837896847",
      "versionName": "9.0.1",
      "versionDate": "2020-09-22T23:57:16.000Z",
      "versionDescription": "腾讯地图国庆专版新鲜出炉，十一轻松出游。\n【新首页，更懂你】智能首页全新升级，丰富工具助你出行，更懂你的出行习惯\n【业界首创整合QQ音乐】十一路上不无聊，用品质导航，听品质音乐，导航听歌两不误\n【附近、消息升级】假期去哪儿不用愁，海量出行资讯全掌握，吃喝玩乐最全推荐\n【路口放大图新升级】国庆驾车长途出游，不怕错过高速出口，精准抵达目的地\n【终点引导精细化】车站机场不迷路，出发到达更精准，少走冤枉路，助你快人一步\n【智能语音助手】长途出行解放双手，全语音操控更智能，叮当一下，开启AI出行\n【性能升级】操作体验更流畅，导航界面更清晰，文字按钮一目了然\n国庆佳节到，腾讯地图祝大家节日快乐！最新版本全新功能，期待体验！",
      "createTime": "2022-04-17T15:13:12.283Z",
      "updateTime": "2022-04-17T15:13:12.283Z",
      "_hasReleaseinfo": true,
      "_isExpand": false
    },
    {
      "id": 31971693,
      "country": "cn",
      "trackId": 481623196,
      "versionId": "837781966",
      "versionName": "9.0.0",
      "versionDate": "2020-09-18T09:19:23.000Z",
      "versionDescription": "腾讯地图全新 V9.0 版本重磅更新，伴随全新品牌升级和多项新功能发布，伴你十一轻松出游！\n【智能首页重构】智能首页全新升级，丰富工具助你出行，更懂你的出行习惯\n【路口放大图新升级】国庆驾车长途出游，不怕错过高速出口，精准抵达目的地\n【终点引导精细化】车站机场不迷路，出发到达更精准，少走冤枉路，助你快人一步\n【智能语音助手】十一长途出行解放双手，全语音操控更智能，叮当一下，开启AI出行\n【性能升级】操作体验更流畅，导航界面更清晰，字体按钮一目了然，更加符合驾驶习惯\n【实时公交】公交出行不用等，进站信息全知道，绿色出行，省时省力\n【附近、消息升级】十一去哪儿不用愁，海量出行资讯全掌握，吃喝玩乐最全推荐",
      "createTime": "2022-04-17T15:13:12.283Z",
      "updateTime": "2022-04-17T15:13:12.283Z",
      "_hasReleaseinfo": true,
      "_isExpand": false
    },
    {
      "id": 31971694,
      "country": "cn",
      "trackId": 481623196,
      "versionId": "837428761",
      "versionName": "8.18.0",
      "versionDate": "2020-08-25T00:58:42.000Z",
      "versionDescription": "【路线指引更详细】道路信息更丰富 驾驶更安心 \r\n【叮当切换更快路线】导航遇堵不发愁 叮当帮你找更快的路\r\n【路口放大图新升级】道路形状一目了然 车道指引准确无误",
      "createTime": "2022-04-17T15:13:12.283Z",
      "updateTime": "2022-04-17T15:13:12.283Z",
      "_hasReleaseinfo": true,
      "_isExpand": false
    },
    {
      "id": 31971695,
      "country": "cn",
      "trackId": 481623196,
      "versionId": "837055257",
      "versionName": "8.17.0",
      "versionDate": "2020-08-03T15:55:28.000Z",
      "versionDescription": "【导航中可点击唤起叮当】点击叮当图标，唤起智能语音助手\r\n【驾车终点智能引导】驾车步行无缝衔接，精准抵达目的地\r\n【导航中可切换车标】点击车标即可换，多套3D皮肤供你选 \r\n【新增附近实时公交提醒】支持查询北京等64城市 实时查看轻松乘车",
      "createTime": "2022-04-17T15:13:12.283Z",
      "updateTime": "2022-04-17T15:13:12.283Z",
      "_hasReleaseinfo": true,
      "_isExpand": false
    },
    {
      "id": 31971696,
      "country": "cn",
      "trackId": 481623196,
      "versionId": "836742643",
      "versionName": "8.16.0",
      "versionDate": "2020-07-10T16:09:03.000Z",
      "versionDescription": "【电动车导航】新增电动车导航 禁行信息、预估时间更准确 \r\n【导航中切换车标】点击车标即可换 多套3D皮肤任你选\r\n【公交信息更丰富】实时查看发车间隔、到站信息 \r\n【导航定位更精准】全新智能定位技术 GPS信号弱时精准导航",
      "createTime": "2022-04-17T15:13:12.283Z",
      "updateTime": "2022-04-17T15:13:12.283Z",
      "_hasReleaseinfo": true,
      "_isExpand": false
    },
    {
      "id": 31971697,
      "country": "cn",
      "trackId": 481623196,
      "versionId": "836353958",
      "versionName": "8.15.0",
      "versionDate": "2020-06-22T16:15:31.000Z",
      "versionDescription": "腾讯地图设计全新升级，操作更便捷\r\n【全新视觉更轻快】设计刷新 产品体验升级\r\n【公交信息更丰富】实时查看发车间隔、到站信息 \r\n【导航定位更精准】全新智能定位技术 GPS信号弱时精准导航\r\n【王者荣耀主题皮肤】英雄超神守护 3D沉浸导航惬意相伴\r\n即刻下载，体验新版本",
      "createTime": "2022-04-17T15:13:12.283Z",
      "updateTime": "2022-04-17T15:13:12.283Z",
      "_hasReleaseinfo": true,
      "_isExpand": false
    },
    {
      "id": 31971698,
      "country": "cn",
      "trackId": 481623196,
      "versionId": "836090396",
      "versionName": "8.14.0",
      "versionDate": "2020-05-15T02:25:26.000Z",
      "versionDescription": "【导航定位体验升级】全新智能定位技术 GPS信号弱时精准导航\r\n【王者荣耀语音包】貂蝉昭君安琪拉 悦动语音轻松出游\r\n【王者荣耀主题皮肤】英雄超神守护 3D沉浸导航惬意相伴\r\n【实时突发路况】异常事件显详情 出行从容不迫",
      "createTime": "2022-04-17T15:13:12.283Z",
      "updateTime": "2022-04-17T15:13:12.283Z",
      "_hasReleaseinfo": true,
      "_isExpand": false
    },
    {
      "id": 31971699,
      "country": "cn",
      "trackId": 481623196,
      "versionId": "835743635",
      "versionName": "8.14.0",
      "versionDate": "2020-05-15T02:25:26.000Z",
      "versionDescription": "【导航定位体验升级】全新智能定位技术 GPS信号弱时精准导航\r\n【王者荣耀语音包】貂蝉昭君安琪拉 悦动语音轻松出游\r\n【王者荣耀主题皮肤】英雄超神守护 3D沉浸导航惬意相伴\r\n【实时突发路况】异常事件显详情 出行从容不迫",
      "createTime": "2022-04-17T15:13:12.283Z",
      "updateTime": "2022-04-17T15:13:12.283Z",
      "_hasReleaseinfo": true,
      "_isExpand": false
    },
    {
      "id": 31971700,
      "country": "cn",
      "trackId": 481623196,
      "versionId": "835676913",
      "versionName": "8.13.1",
      "versionDate": "2020-04-28T01:40:35.000Z",
      "versionDescription": "王者荣耀英雄入驻，五一与你为伍\r\n【王者荣耀语音包】：貂蝉昭君安琪拉 悦动语音轻松出游\r\n【王者荣耀主题地图】：英雄超神守护 3D沉浸导航惬意相伴\r\n【实时突发路况】：异常事件显详情 五一出游从容不迫\r\n王者出行，这个五一更有趣",
      "createTime": "2022-04-17T15:13:12.283Z",
      "updateTime": "2022-04-17T15:13:12.283Z",
      "_hasReleaseinfo": true,
      "_isExpand": false
    },
    {
      "id": 31971701,
      "country": "cn",
      "trackId": 481623196,
      "versionId": "835616784",
      "versionName": "8.13.0",
      "versionDate": "2020-04-22T01:54:19.000Z",
      "versionDescription": "【路况事件实时掌握】道路事件实时提示  突发问题随时掌握\r\n【一键叫车安全出发】西安东莞率先上线打车功能 更多城市陆续上线中\r\n【行驶路线解释更详细】路线显示样式升级  轮渡路线清晰直观",
      "createTime": "2022-04-17T15:13:12.283Z",
      "updateTime": "2022-04-17T15:13:12.283Z",
      "_hasReleaseinfo": true,
      "_isExpand": false
    },
    {
      "id": 31971702,
      "country": "cn",
      "trackId": 481623196,
      "versionId": "835488890",
      "versionName": "8.12.2",
      "versionDate": "2020-04-14T02:22:42.000Z",
      "versionDescription": "【性能优化】优化产品体验\r\n【路口大图全新上线】新增多种路口场景 完美复刻真实道路\r\n【公交、步骑行体验升级】展示终点出入口信息 更准确到达终点",
      "createTime": "2022-04-17T15:13:12.283Z",
      "updateTime": "2022-04-17T15:13:12.283Z",
      "_hasReleaseinfo": true,
      "_isExpand": false
    },
    {
      "id": 31971703,
      "country": "cn",
      "trackId": 481623196,
      "versionId": "835433106",
      "versionName": "8.12.1",
      "versionDate": "2020-04-10T02:23:54.000Z",
      "versionDescription": "【性能优化】优化产品体验\r\n【路口大图全新上线】新增多种路口场景 完美复刻真实道路\r\n【公交、步骑行体验升级】展示终点出入口信息 更准确到达终点",
      "createTime": "2022-04-17T15:13:12.283Z",
      "updateTime": "2022-04-17T15:13:12.283Z",
      "_hasReleaseinfo": true,
      "_isExpand": false
    },
    {
      "id": 31971704,
      "country": "cn",
      "trackId": 481623196,
      "versionId": "835154610",
      "versionName": "8.12.0",
      "versionDate": "2020-03-19T00:03:00.000Z",
      "versionDescription": "【路口大图全新上线】新增多种路口场景 完美复刻真实道路\r\n【公交、步骑行体验升级】展示终点出入口信息 更准确到达终点\r\n【地铁舒适度】可查看广州地铁拥挤情况 其他城市陆续上线中\r\n【电子眼呈现优化】电子眼显示优化  图面显示更简洁",
      "createTime": "2022-04-17T15:13:12.283Z",
      "updateTime": "2022-04-17T15:13:12.283Z",
      "_hasReleaseinfo": true,
      "_isExpand": false
    },
    {
      "id": 31971705,
      "country": "cn",
      "trackId": 481623196,
      "versionId": "834933929",
      "versionName": "8.11.1",
      "versionDate": "2020-03-03T00:07:33.000Z",
      "versionDescription": "【地铁舒适度】可查看广州地铁拥挤情况 其他城市陆续上线中\r\n【电子眼呈现优化】电子眼显示优化  图面显示更简洁\r\n【限行功能升级】路线规划增加限行开关 一键切换更方便",
      "createTime": "2022-04-17T15:13:12.283Z",
      "updateTime": "2022-04-17T15:13:12.283Z",
      "_hasReleaseinfo": true,
      "_isExpand": false
    },
    {
      "id": 31971706,
      "country": "cn",
      "trackId": 481623196,
      "versionId": "834835166",
      "versionName": "8.11.0",
      "versionDate": "2020-02-25T00:23:58.000Z",
      "versionDescription": "【电子眼呈现优化】电子眼显示优化  图面显示更简洁\r\n【限行功能升级】路线规划增加限行开关 一键切换更方便 \r\n【疫情小区地图】共抗疫情 身边新冠肺炎疫情实时查",
      "createTime": "2022-04-17T15:13:12.283Z",
      "updateTime": "2022-04-17T15:13:12.283Z",
      "_hasReleaseinfo": true,
      "_isExpand": false
    },
    {
      "id": 31971707,
      "country": "cn",
      "trackId": 481623196,
      "versionId": "834666735",
      "versionName": "8.10.2",
      "versionDate": "2020-02-19T00:13:59.000Z",
      "versionDescription": "腾讯地图已上线新冠肺炎疫情小区查询功能，快捷查询周围确诊病例小区、与我距离和疫情地图等信息。身边疫情实时查，共抗疫情，我们与你在一起！",
      "createTime": "2022-04-17T15:13:12.283Z",
      "updateTime": "2022-04-17T15:13:12.283Z",
      "_hasReleaseinfo": true,
      "_isExpand": false
    },
    {
      "id": 31971708,
      "country": "cn",
      "trackId": 481623196,
      "versionId": "834415526",
      "versionName": "8.10.1",
      "versionDate": "2020-01-22T16:59:09.000Z",
      "versionDescription": "腾讯地图全新春节版发布，陪你春节快乐出行\n【语音助手换新】叮当全新形象登场 解放双手导航更轻松\n【路线规划体验升级】终点信息多元展现 春节出游心中有数\n【春运报平安】一键分享回家路线 实时位置亲人一目了然\n【步骑行多方案】新增多路线规划 出行选择更灵活\n【特殊车道线提示】特殊车道不误入 妈妈奖励我烤山药",
      "createTime": "2022-04-17T15:13:12.283Z",
      "updateTime": "2022-04-17T15:13:12.283Z",
      "_hasReleaseinfo": true,
      "_isExpand": false
    },
    {
      "id": 31971709,
      "country": "cn",
      "trackId": 481623196,
      "versionId": "834281539",
      "versionName": "8.10.0",
      "versionDate": "2020-01-17T20:03:24.000Z",
      "versionDescription": "腾讯地图全新春节版发布，陪你春节快乐出行 \r\n【语音助手换新】叮当全新形象登场 解放双手导航更轻松\r\n【路线规划体验升级】终点信息多元展现 春节出游心中有数\r\n【春运报平安】一键分享回家路线 实时位置亲人一目了然\r\n【步骑行多方案】新增多路线规划 出行选择更灵活\r\n【特殊车道线提示】特殊车道不误入 妈妈奖励我烤山药 ",
      "createTime": "2022-04-17T15:13:12.283Z",
      "updateTime": "2022-04-17T15:13:12.283Z",
      "_hasReleaseinfo": true,
      "_isExpand": false
    },
    {
      "id": 31971710,
      "country": "cn",
      "trackId": 481623196,
      "versionId": "834019574",
      "versionName": "8.9.10",
      "versionDate": "2019-12-19T00:51:23.000Z",
      "versionDescription": "【定位功能升级】定位更快更精准 高架桥上不迷路\r\n【优惠乘车】刷码乘公交低至1分钱 覆盖重庆深圳80城\r\n【多途径点算路】支持多个途经点 行程规划更便捷",
      "createTime": "2022-04-17T15:13:12.283Z",
      "updateTime": "2022-04-17T15:13:12.283Z",
      "_hasReleaseinfo": true,
      "_isExpand": false
    },
    {
      "id": 31971711,
      "country": "cn",
      "trackId": 481623196,
      "versionId": "833929799",
      "versionName": "8.9.9",
      "versionDate": "2019-12-10T23:41:39.000Z",
      "versionDescription": "【优惠乘车】刷码乘公交低至1分钱 覆盖重庆深圳80城\r\n【多途径点算路】支持多个途经点 行程规划更便捷 \r\n【电子眼升级】电子眼体验优化 远离违章少罚款\r\n【实时公交】实时公交全新升级 25城市抢先体验",
      "createTime": "2022-04-17T15:13:12.283Z",
      "updateTime": "2022-04-17T15:13:12.283Z",
      "_hasReleaseinfo": true,
      "_isExpand": false
    },
    {
      "id": 31971712,
      "country": "cn",
      "trackId": 481623196,
      "versionId": "833742456",
      "versionName": "8.9.8",
      "versionDate": "2019-12-03T23:46:26.000Z",
      "versionDescription": "支持多个途经点算路 行程规划更便捷；\r\n电子眼体验优化 远离违章少罚款；\r\n实时公交全新升级 21城市抢先体验；\r\n乘车码刷码乘车  无需购票带卡一键刷。",
      "createTime": "2022-04-17T15:13:12.283Z",
      "updateTime": "2022-04-17T15:13:12.283Z",
      "_hasReleaseinfo": true,
      "_isExpand": false
    },
    {
      "id": 31971713,
      "country": "cn",
      "trackId": 481623196,
      "versionId": "833526986",
      "versionName": "8.9.6",
      "versionDate": "2019-11-15T00:08:08.000Z",
      "versionDescription": "实时公交全新升级  广州深圳等15城市抢先体验\r\n乘车码刷码乘车  无需购票带卡一键刷码更便捷                                                            \r\n城市页卡贴心上线  本地吃喝玩乐全攻略一键开启\r\n性能卓越升级  启动更快体验更流畅",
      "createTime": "2022-04-17T15:13:12.283Z",
      "updateTime": "2022-04-17T15:13:12.283Z",
      "_hasReleaseinfo": true,
      "_isExpand": false
    },
    {
      "id": 31971714,
      "country": "cn",
      "trackId": 481623196,
      "versionId": "833189763",
      "versionName": "8.9.5",
      "versionDate": "2019-11-07T23:39:58.000Z",
      "versionDescription": "实时公交全新升级  广州深圳等15城市抢先体验\r\n乘车码刷码乘车  无需购票带卡一键刷码更便捷                                                            \r\n城市页卡贴心上线  本地吃喝玩乐全攻略一键开启\r\n性能卓越升级  启动更快体验更流畅",
      "createTime": "2022-04-17T15:13:12.283Z",
      "updateTime": "2022-04-17T15:13:12.283Z",
      "_hasReleaseinfo": true,
      "_isExpand": false
    },
    {
      "id": 31971715,
      "country": "cn",
      "trackId": 481623196,
      "versionId": "833079128",
      "versionName": "8.9.3",
      "versionDate": "2019-10-08T23:46:25.000Z",
      "versionDescription": "【本次更新】 \n修复 iOS 13 CarPlay 在后台无法开始导航的问题\n\n【最近更新】 \n性能全面升级，启动更快体验更流畅\n全新导航视觉，重要信息更醒目操作便捷更安全\n城市页卡贴心上线，本地吃喝玩乐全攻略一键开启",
      "createTime": "2022-04-17T15:13:12.283Z",
      "updateTime": "2022-04-17T15:13:12.283Z",
      "_hasReleaseinfo": true,
      "_isExpand": false
    },
    {
      "id": 31971716,
      "country": "cn",
      "trackId": 481623196,
      "versionId": "832973666",
      "versionName": "8.9.2",
      "versionDate": "2019-10-02T16:13:57.000Z",
      "versionDescription": "【本次更新】 \n修复 iOS 13 CarPlay 无法开始导航的问题\n修复电子眼可能不显示的问题\n\n【最近更新】 \n性能全面升级，启动更快体验更流畅\n全新导航视觉，重要信息更醒目操作便捷更安全\n城市页卡贴心上线，本地吃喝玩乐全攻略一键开启",
      "createTime": "2022-04-17T15:13:12.283Z",
      "updateTime": "2022-04-17T15:13:12.283Z",
      "_hasReleaseinfo": true,
      "_isExpand": false
    },
    {
      "id": 31971717,
      "country": "cn",
      "trackId": 481623196,
      "versionId": "832893040",
      "versionName": "8.9.1",
      "versionDate": "2019-09-25T01:03:17.000Z",
      "versionDescription": "【本次更新】 \r\n性能全面升级，启动更快体验更流畅\r\n全新导航视觉，重要信息更醒目操作便捷更安全\r\n城市页卡贴心上线，本地吃喝玩乐全攻略一键开启",
      "createTime": "2022-04-17T15:13:12.283Z",
      "updateTime": "2022-04-17T15:13:12.283Z",
      "_hasReleaseinfo": true,
      "_isExpand": false
    },
    {
      "id": 31971718,
      "country": "cn",
      "trackId": 481623196,
      "versionId": "832788350",
      "versionName": "8.9.0",
      "versionDate": "2019-09-23T16:12:23.000Z",
      "versionDescription": "【本次更新】 \r\n性能全面升级，启动更快体验更流畅\r\n全新导航视觉，重要信息更醒目操作便捷更安全\r\n城市页卡贴心上线，本地吃喝玩乐全攻略一键开启",
      "createTime": "2022-04-17T15:13:12.283Z",
      "updateTime": "2022-04-17T15:13:12.283Z",
      "_hasReleaseinfo": true,
      "_isExpand": false
    },
    {
      "id": 31971719,
      "country": "cn",
      "trackId": 481623196,
      "versionId": "832375190",
      "versionName": "8.8.5",
      "versionDate": "2019-08-17T01:21:09.000Z",
      "versionDescription": "【本次更新】\r\n积水地图上线 雨季出行更安心\r\n充电站全面优化 找桩充电更轻松\r\n定位体验升级 减少等待秒出行\r\n【最近更新】\r\n电子眼体验升级 安全驾驶避违章\r\n性能全面优化 加载更快更流畅",
      "createTime": "2022-04-17T15:13:12.283Z",
      "updateTime": "2022-04-17T15:13:12.283Z",
      "_hasReleaseinfo": true,
      "_isExpand": false
    },
    {
      "id": 31971720,
      "country": "cn",
      "trackId": 481623196,
      "versionId": "832145440",
      "versionName": "8.8.0",
      "versionDate": "2019-07-27T02:50:46.000Z",
      "versionDescription": "性能全面优化 加载更快更流畅\n电子眼体验升级 安全驾驶避违章\n全新3D室内图 逛街找店不迷路 ",
      "createTime": "2022-04-17T15:13:12.283Z",
      "updateTime": "2022-04-17T15:13:12.283Z",
      "_hasReleaseinfo": true,
      "_isExpand": false
    },
    {
      "id": 31971721,
      "country": "cn",
      "trackId": 481623196,
      "versionId": "832038151",
      "versionName": "8.7.9",
      "versionDate": "2019-07-17T19:49:06.000Z",
      "versionDescription": "【本次更新】\n性能全面优化 加载更快更流畅\n【最近更新】\n电子眼体验升级 安全驾驶避违章\n全新3D室内图 逛街找店不迷路 \n路线规划更迅捷 减少等待秒出行 \n精选酒店安心订 价格口碑随时查",
      "createTime": "2022-04-17T15:13:12.283Z",
      "updateTime": "2022-04-17T15:13:12.283Z",
      "_hasReleaseinfo": true,
      "_isExpand": false
    },
    {
      "id": 31971722,
      "country": "cn",
      "trackId": 481623196,
      "versionId": "831973319",
      "versionName": "8.7.8",
      "versionDate": "2019-07-16T23:36:50.000Z",
      "versionDescription": "【本次更新】\r\n性能全面优化  加载更快更流畅\r\n【最近更新】\r\n电子眼体验升级 安全驾驶避违章\r\n全新3D室内图 逛街找店不迷路 \r\n路线规划更迅捷 减少等待秒出行 \r\n精选酒店安心订 价格口碑随时查",
      "createTime": "2022-04-17T15:13:12.283Z",
      "updateTime": "2022-04-17T15:13:12.283Z",
      "_hasReleaseinfo": true,
      "_isExpand": false
    },
    {
      "id": 31971723,
      "country": "cn",
      "trackId": 481623196,
      "versionId": "831814185",
      "versionName": "8.7.7",
      "versionDate": "2019-07-02T22:59:27.000Z",
      "versionDescription": "【本次更新】 \r\n电子眼体验升级 安全驾驶避违章 \r\n【最近更新】 \r\n性能全面升级 启动更快更流畅 \r\n全新3D室内图 逛街找店不迷路 \r\n路线规划更迅捷 减少等待秒出行 \r\n精选酒店安心订 价格口碑随时查",
      "createTime": "2022-04-17T15:13:12.283Z",
      "updateTime": "2022-04-17T15:13:12.283Z",
      "_hasReleaseinfo": true,
      "_isExpand": false
    },
    {
      "id": 31971724,
      "country": "cn",
      "trackId": 481623196,
      "versionId": "831743780",
      "versionName": "8.7.6",
      "versionDate": "2019-06-21T16:28:40.000Z",
      "versionDescription": "【本次更新】\r\n电子眼体验升级 安全驾驶避违章\r\n【最近更新】\r\n性能全面升级 启动更快更流畅\r\n全新3D室内图 逛街找店不迷路\r\n路线规划更迅捷 减少等待秒出行\r\n精选酒店安心订 价格口碑随时查",
      "createTime": "2022-04-17T15:13:12.283Z",
      "updateTime": "2022-04-17T15:13:12.283Z",
      "_hasReleaseinfo": true,
      "_isExpand": false
    },
    {
      "id": 31971725,
      "country": "cn",
      "trackId": 481623196,
      "versionId": "831718437",
      "versionName": "8.7.5",
      "versionDate": "2019-06-20T22:12:13.000Z",
      "versionDescription": "【本次更新】\n电子眼体验升级 安全驾驶避违章\n【最近更新】\n性能全面升级 启动更快更流畅\n全新3D室内图 逛街找店不迷路\n路线规划更迅捷 减少等待秒出行\n精选酒店安心订 价格口碑随时查",
      "createTime": "2022-04-17T15:13:12.283Z",
      "updateTime": "2022-04-17T15:13:12.283Z",
      "_hasReleaseinfo": true,
      "_isExpand": false
    },
    {
      "id": 31971726,
      "country": "cn",
      "trackId": 481623196,
      "versionId": "831548360",
      "versionName": "8.7.0",
      "versionDate": "2019-06-06T23:47:13.000Z",
      "versionDescription": "性能全面升级  启动更快更流畅；\n全新3D室内图  逛街找店不迷路；\n路线规划更迅捷  减少等待秒出行；\n精选酒店安心订 价格口碑随时查；\n景点信息丰富 旅游出行更省心。",
      "createTime": "2022-04-17T15:13:12.283Z",
      "updateTime": "2022-04-17T15:13:12.283Z",
      "_hasReleaseinfo": true,
      "_isExpand": false
    },
    {
      "id": 31971727,
      "country": "cn",
      "trackId": 481623196,
      "versionId": "831371686",
      "versionName": "8.6.6",
      "versionDate": "2019-05-23T21:48:03.000Z",
      "versionDescription": "-精选酒店安心订 价格口碑随时查\n-定位更快更流畅 减少等待秒出行",
      "createTime": "2022-04-17T15:13:12.283Z",
      "updateTime": "2022-04-17T15:13:12.283Z",
      "_hasReleaseinfo": true,
      "_isExpand": false
    },
    {
      "id": 31971728,
      "country": "cn",
      "trackId": 481623196,
      "versionId": "831312132",
      "versionName": "8.6.5",
      "versionDate": "2019-05-19T00:50:36.000Z",
      "versionDescription": "-精选酒店安心订 价格口碑随时查\n-定位更快更流畅 减少等待秒出行",
      "createTime": "2022-04-17T15:13:12.283Z",
      "updateTime": "2022-04-17T15:13:12.283Z",
      "_hasReleaseinfo": true,
      "_isExpand": false
    },
    {
      "id": 31971729,
      "country": "cn",
      "trackId": 481623196,
      "versionId": "831144428",
      "versionName": "8.6.2",
      "versionDate": "2019-05-01T16:30:34.000Z",
      "versionDescription": "关爱专职司机，劳动节导航送现金\n景点信息更丰富，五一出行更省心\n实时推荐精准路线，躲避拥堵更快捷\n语音输入解放双手，贴心服务开口即达\n完美支持CarPlay，一键投屏车载导航",
      "createTime": "2022-04-17T15:13:12.283Z",
      "updateTime": "2022-04-17T15:13:12.283Z",
      "_hasReleaseinfo": true,
      "_isExpand": false
    },
    {
      "id": 31971730,
      "country": "cn",
      "trackId": 481623196,
      "versionId": "831129997",
      "versionName": "8.6.1",
      "versionDate": "2019-04-27T23:11:52.000Z",
      "versionDescription": "关爱专职司机，劳动节导航送现金\n景点信息更丰富，五一出行更省心\n实时推荐精准路线，躲避拥堵更快捷\n语音输入解放双手，贴心服务开口即达\n完美支持CarPlay，一键投屏车载导航",
      "createTime": "2022-04-17T15:13:12.283Z",
      "updateTime": "2022-04-17T15:13:12.283Z",
      "_hasReleaseinfo": true,
      "_isExpand": false
    },
    {
      "id": 31971731,
      "country": "cn",
      "trackId": 481623196,
      "versionId": "831102810",
      "versionName": "8.6.0",
      "versionDate": "2019-04-26T02:01:17.000Z",
      "versionDescription": "关爱专职司机，劳动节导航送现金\n景点信息更丰富，五一出行更省心\n实时推荐精准路线，躲避拥堵更快捷\n语音输入解放双手，贴心服务开口即达\n完美支持CarPlay，一键投屏车载导航",
      "createTime": "2022-04-17T15:13:12.283Z",
      "updateTime": "2022-04-17T15:13:12.283Z",
      "_hasReleaseinfo": true,
      "_isExpand": false
    },
    {
      "id": 31971732,
      "country": "cn",
      "trackId": 481623196,
      "versionId": "830986420",
      "versionName": "8.5.5",
      "versionDate": "2019-04-23T01:56:23.000Z",
      "versionDescription": "【完美支持CarPlay】一键投屏车载导航\n【支持Siri捷径】呼唤Siri，回家上班更方便\n【赏花地图】清明踏青去哪里 地图带你来赏花\n【景点信息丰富】新增游玩攻略、运营时间 旅游出行更省心\n【电子眼数据更新】覆盖全国全部类型电子眼\n【搜索查限行】限行信息随时查 春游畅快出行",
      "createTime": "2022-04-17T15:13:12.283Z",
      "updateTime": "2022-04-17T15:13:12.283Z",
      "_hasReleaseinfo": true,
      "_isExpand": false
    },
    {
      "id": 31971733,
      "country": "cn",
      "trackId": 481623196,
      "versionId": "830735096",
      "versionName": "8.5.0",
      "versionDate": "2019-04-03T01:04:33.000Z",
      "versionDescription": "【完美支持CarPlay】一键投屏车载导航\n【支持Siri捷径】呼唤Siri，回家上班更方便\n【赏花地图】清明踏青去哪里 地图带你来赏花\n【景点信息丰富】新增游玩攻略、运营时间 旅游出行更省心\n【电子眼数据更新】覆盖全国全部类型电子眼\n【搜索查限行】限行信息随时查 春游畅快出行",
      "createTime": "2022-04-17T15:13:12.283Z",
      "updateTime": "2022-04-17T15:13:12.283Z",
      "_hasReleaseinfo": true,
      "_isExpand": false
    },
    {
      "id": 31971734,
      "country": "cn",
      "trackId": 481623196,
      "versionId": "830667082",
      "versionName": "8.4.9",
      "versionDate": "2019-03-22T21:55:57.000Z",
      "versionDescription": "【完美支持CarPlay】一键投屏车载导航；\n【支持Siri捷径】呼唤Siri，回家上班更方便；\n【智能导航】多路线精准推荐，躲避拥堵更快捷；\n【智能语音助手】语音输入解放双手，贴心服务开口即达；\n【便捷公交服务】到站信息实时更新，乘车更方便；\n【地点信息升级】服务内容更丰富，搜索地点立刻体验。",
      "createTime": "2022-04-17T15:13:12.283Z",
      "updateTime": "2022-04-17T15:13:12.283Z",
      "_hasReleaseinfo": true,
      "_isExpand": false
    },
    {
      "id": 31971735,
      "country": "cn",
      "trackId": 481623196,
      "versionId": "830613609",
      "versionName": "8.4.8",
      "versionDate": "2019-03-15T10:24:14.000Z",
      "versionDescription": "【完美支持CarPlay】一键投屏车载导航；\n【支持Siri捷径】呼唤Siri，回家上班更方便；\n【智能导航】多路线精准推荐，躲避拥堵更快捷；\n【智能语音助手】语音输入解放双手，贴心服务开口即达；\n【便捷公交服务】到站信息实时更新，乘车更方便；\n【地点信息升级】服务内容更丰富，搜索地点立刻体验。",
      "createTime": "2022-04-17T15:13:12.283Z",
      "updateTime": "2022-04-17T15:13:12.283Z",
      "_hasReleaseinfo": true,
      "_isExpand": false
    },
    {
      "id": 31971736,
      "country": "cn",
      "trackId": 481623196,
      "versionId": "830451929",
      "versionName": "8.4.5",
      "versionDate": "2019-03-13T21:17:54.000Z",
      "versionDescription": "【完美支持CarPlay】一键投屏车载导航；\n【新增房产信息】小区信息随手查 租房买房更省心；\n【智能导航】多路线精准推荐，躲避拥堵更快捷；\n【智能语音助手】语音输入解放双手，贴心服务开口即达；\n【便捷公交服务】到站信息实时更新，乘车更方便。",
      "createTime": "2022-04-17T15:13:12.283Z",
      "updateTime": "2022-04-17T15:13:12.283Z",
      "_hasReleaseinfo": true,
      "_isExpand": false
    },
    {
      "id": 31971737,
      "country": "cn",
      "trackId": 481623196,
      "versionId": "830122631",
      "versionName": "8.4.1",
      "versionDate": "2019-01-30T20:04:22.000Z",
      "versionDescription": "【完美支持CarPlay】一键投屏车载导航；\n【春节特色语音播报】各省明星送祝福 ，暖心回家路；\n【长途跨城方案】春节回家，火车换乘方案随时查；\n【智能语音助手】贴心服务开口即达，自驾回家更安全；\n【美食信息优化】过年聚会查附近美食，更有排队信息；\n【伴随路线优化】实时智能避堵，春节早回家。",
      "createTime": "2022-04-17T15:13:12.283Z",
      "updateTime": "2022-04-17T15:13:12.283Z",
      "_hasReleaseinfo": true,
      "_isExpand": false
    },
    {
      "id": 31971738,
      "country": "cn",
      "trackId": 481623196,
      "versionId": "830090306",
      "versionName": "8.4.0",
      "versionDate": "2019-01-26T19:47:23.000Z",
      "versionDescription": "【春节特色语音播报】各省明星送祝福，暖心回家路\n【长途跨城方案】春节回家，火车换乘方案随时查\n【智能语音助手】贴心服务开口即达，自驾回家更安全\n【美食信息优化】过年聚会查附近美食，更有排队信息\n【伴随路线优化】实时智能避堵，春节早回家",
      "createTime": "2022-04-17T15:13:12.283Z",
      "updateTime": "2022-04-17T15:13:12.283Z",
      "_hasReleaseinfo": true,
      "_isExpand": false
    },
    {
      "id": 31971739,
      "country": "cn",
      "trackId": 481623196,
      "versionId": "829971052",
      "versionName": "8.3.7",
      "versionDate": "2019-01-16T21:03:09.000Z",
      "versionDescription": "【详情页优化】房产小区与景点信息更丰富；\n【智能语音助手】新增景点类问答能力；\n【长途跨城方案】支持查询城市间的火车换乘方案；\n【公交支付】支持使用乘车码扫码乘车；\n【定制公交地图】优化公交地图信息，线路换乘更清晰。",
      "createTime": "2022-04-17T15:13:12.283Z",
      "updateTime": "2022-04-17T15:13:12.283Z",
      "_hasReleaseinfo": true,
      "_isExpand": false
    },
    {
      "id": 31971740,
      "country": "cn",
      "trackId": 481623196,
      "versionId": "829776522",
      "versionName": "8.3.5",
      "versionDate": "2018-12-28T18:49:26.000Z",
      "versionDescription": "【详情页优化】房产小区与景点信息更丰富；\n【智能语音助手】新增景点类问答能力；\n【长途跨城方案】支持查询城市间的火车换乘方案；\n【公交支付】支持使用乘车码扫码乘车；\n【定制公交地图】优化公交地图信息，线路换乘更清晰。",
      "createTime": "2022-04-17T15:13:12.283Z",
      "updateTime": "2022-04-17T15:13:12.283Z",
      "_hasReleaseinfo": true,
      "_isExpand": false
    },
    {
      "id": 31971741,
      "country": "cn",
      "trackId": 481623196,
      "versionId": "829675966",
      "versionName": "8.3.1",
      "versionDate": "2018-12-18T01:56:07.000Z",
      "versionDescription": "【长途跨城方案】支持查询城市间的火车换乘方案；\n【公交支付】支持使用乘车码扫码乘车；\n【定制公交地图】优化公交地图信息，线路换乘更清晰；\n【地图字号调节】四种字号设置，给你最好的看图体验；\n【搜索优化】搜索结果页结构优化，关键信息更清晰。",
      "createTime": "2022-04-17T15:13:12.283Z",
      "updateTime": "2022-04-17T15:13:12.283Z",
      "_hasReleaseinfo": true,
      "_isExpand": false
    },
    {
      "id": 31971742,
      "country": "cn",
      "trackId": 481623196,
      "versionId": "829627929",
      "versionName": "8.3.0",
      "versionDate": "2018-12-14T03:07:29.000Z",
      "versionDescription": "【长途跨城方案】支持查询城市间的火车换乘方案；\n【公交支付】支持使用乘车码扫码乘车；\n【定制公交地图】优化公交地图信息，线路换乘更清晰；\n【地图字号调节】四种字号设置，给你最好的看图体验；\n【搜索优化】搜索结果页结构优化，关键信息更清晰。",
      "createTime": "2022-04-17T15:13:12.283Z",
      "updateTime": "2022-04-17T15:13:12.283Z",
      "_hasReleaseinfo": true,
      "_isExpand": false
    },
    {
      "id": 31971743,
      "country": "cn",
      "trackId": 481623196,
      "versionId": "829458631",
      "versionName": "8.2.0",
      "versionDate": "2018-12-04T00:02:35.000Z",
      "versionDescription": "【定制公交地图】优化公交地图信息，线路换乘更清晰；\n【地图字号调节】四种字号设置，给你最好的看图体验；\n【搜索优化】支持精准地图区域范围内搜索；\n【导航路口增强】转向路口更突出；\n【实时公交】实时查看公交到站信息，等车不着急。",
      "createTime": "2022-04-17T15:13:12.283Z",
      "updateTime": "2022-04-17T15:13:12.283Z",
      "_hasReleaseinfo": true,
      "_isExpand": false
    },
    {
      "id": 31971744,
      "country": "cn",
      "trackId": 481623196,
      "versionId": "829343860",
      "versionName": "8.1.9",
      "versionDate": "2018-11-20T18:07:22.000Z",
      "versionDescription": "【运营时间提醒】出发之前搜一搜，再也不吃『闭门羹』；\n【搜索优化】搜索结果页结构优化，关键信息更清晰。",
      "createTime": "2022-04-17T15:13:12.283Z",
      "updateTime": "2022-04-17T15:13:12.283Z",
      "_hasReleaseinfo": true,
      "_isExpand": false
    },
    {
      "id": 31971745,
      "country": "cn",
      "trackId": 481623196,
      "versionId": "829301093",
      "versionName": "8.1.8",
      "versionDate": "2018-11-15T20:00:06.000Z",
      "versionDescription": "【运营时间提醒】出发之前搜一搜，再也不吃『闭门羹』；\n【搜索优化】搜索结果页结构优化，关键信息更清晰。",
      "createTime": "2022-04-17T15:13:12.283Z",
      "updateTime": "2022-04-17T15:13:12.283Z",
      "_hasReleaseinfo": true,
      "_isExpand": false
    },
    {
      "id": 31971746,
      "country": "cn",
      "trackId": 481623196,
      "versionId": "829143733",
      "versionName": "8.1.7",
      "versionDate": "2018-11-02T21:49:31.000Z",
      "versionDescription": "完美适配iPhone XS，iPhone XS Max\n【加油站信息优化】支持查看加油站的油号、价格等信息；\n【路口增强】导航指示更明确，转向路口道路显示更突出；\n【主题广场】特色主题全新上线，你的地图你来定义；\n【实时公交】实时查看公交到站情况，等车不着急；\n【智能语音助手】语音助手更智能，说『叮当叮当』，贴心服务开口即达。",
      "createTime": "2022-04-17T15:13:12.283Z",
      "updateTime": "2022-04-17T15:13:12.283Z",
      "_hasReleaseinfo": true,
      "_isExpand": false
    },
    {
      "id": 31971747,
      "country": "cn",
      "trackId": 481623196,
      "versionId": "828972154",
      "versionName": "8.1.5",
      "versionDate": "2018-10-18T20:11:00.000Z",
      "versionDescription": "【路口增强】导航指示更明确，转向路口道路显示更突出；\n【主题广场】特色主题全新上线，你的地图你来定义；\n【实时公交】实时查看公交到站情况，支持13个城市的实时公交信息；\n【3D地图】还原最真实的世界，支持20个城市的3D地图效果；\n【智能语音助手】语音助手更智能，说『叮当叮当』，贴心服务开口即达。",
      "createTime": "2022-04-17T15:13:12.283Z",
      "updateTime": "2022-04-17T15:13:12.283Z",
      "_hasReleaseinfo": true,
      "_isExpand": false
    },
    {
      "id": 31971748,
      "country": "cn",
      "trackId": 481623196,
      "versionId": "828800818",
      "versionName": "8.1.1",
      "versionDate": "2018-10-04T15:21:09.000Z",
      "versionDescription": "【实时公交】实时查看公交到站信息，等车不着急；\n【3D地图】还原最真实的世界，支持20个城市的3D地图效果；\n【智能语音助手】语音助手更智能，说『叮当叮当』，贴心服务开口即达；\n【智能导航】智能调整诱导播报，导航指引更及时准确。",
      "createTime": "2022-04-17T15:13:12.283Z",
      "updateTime": "2022-04-17T15:13:12.283Z",
      "_hasReleaseinfo": true,
      "_isExpand": false
    },
    {
      "id": 31971749,
      "country": "cn",
      "trackId": 481623196,
      "versionId": "828720252",
      "versionName": "8.2.0",
      "versionDate": "2018-12-04T00:02:35.000Z",
      "versionDescription": "【定制公交地图】优化公交地图信息，线路换乘更清晰；\n【地图字号调节】四种字号设置，给你最好的看图体验；\n【搜索优化】支持精准地图区域范围内搜索；\n【导航路口增强】转向路口更突出；\n【实时公交】实时查看公交到站信息，等车不着急。",
      "createTime": "2022-04-17T15:13:12.283Z",
      "updateTime": "2022-04-17T15:13:12.283Z",
      "_hasReleaseinfo": true,
      "_isExpand": false
    },
    {
      "id": 31971750,
      "country": "cn",
      "trackId": 481623196,
      "versionId": "828720252",
      "versionName": "8.4.9",
      "versionDate": "2019-03-22T21:55:57.000Z",
      "versionDescription": "【完美支持CarPlay】一键投屏车载导航；\n【支持Siri捷径】呼唤Siri，回家上班更方便；\n【智能导航】多路线精准推荐，躲避拥堵更快捷；\n【智能语音助手】语音输入解放双手，贴心服务开口即达；\n【便捷公交服务】到站信息实时更新，乘车更方便；\n【地点信息升级】服务内容更丰富，搜索地点立刻体验。",
      "createTime": "2022-04-17T15:13:12.283Z",
      "updateTime": "2022-04-17T15:13:12.283Z",
      "_hasReleaseinfo": true,
      "_isExpand": false
    },
    {
      "id": 31971751,
      "country": "cn",
      "trackId": 481623196,
      "versionId": "828720252",
      "versionName": "8.4.5",
      "versionDate": "2019-03-13T21:17:54.000Z",
      "versionDescription": "【完美支持CarPlay】一键投屏车载导航；\n【新增房产信息】小区信息随手查 租房买房更省心；\n【智能导航】多路线精准推荐，躲避拥堵更快捷；\n【智能语音助手】语音输入解放双手，贴心服务开口即达；\n【便捷公交服务】到站信息实时更新，乘车更方便。",
      "createTime": "2022-04-17T15:13:12.283Z",
      "updateTime": "2022-04-17T15:13:12.283Z",
      "_hasReleaseinfo": true,
      "_isExpand": false
    },
    {
      "id": 31971752,
      "country": "cn",
      "trackId": 481623196,
      "versionId": "828720252",
      "versionName": "8.4.8",
      "versionDate": "2019-03-15T10:24:14.000Z",
      "versionDescription": "【完美支持CarPlay】一键投屏车载导航；\n【支持Siri捷径】呼唤Siri，回家上班更方便；\n【智能导航】多路线精准推荐，躲避拥堵更快捷；\n【智能语音助手】语音输入解放双手，贴心服务开口即达；\n【便捷公交服务】到站信息实时更新，乘车更方便；\n【地点信息升级】服务内容更丰富，搜索地点立刻体验。",
      "createTime": "2022-04-17T15:13:12.283Z",
      "updateTime": "2022-04-17T15:13:12.283Z",
      "_hasReleaseinfo": true,
      "_isExpand": false
    },
    {
      "id": 31971753,
      "country": "cn",
      "trackId": 481623196,
      "versionId": "828720252",
      "versionName": "8.4.1",
      "versionDate": "2019-01-30T20:04:22.000Z",
      "versionDescription": "【完美支持CarPlay】一键投屏车载导航；\n【春节特色语音播报】各省明星送祝福 ，暖心回家路；\n【长途跨城方案】春节回家，火车换乘方案随时查；\n【智能语音助手】贴心服务开口即达，自驾回家更安全；\n【美食信息优化】过年聚会查附近美食，更有排队信息；\n【伴随路线优化】实时智能避堵，春节早回家。",
      "createTime": "2022-04-17T15:13:12.283Z",
      "updateTime": "2022-04-17T15:13:12.283Z",
      "_hasReleaseinfo": true,
      "_isExpand": false
    },
    {
      "id": 31971754,
      "country": "cn",
      "trackId": 481623196,
      "versionId": "828720252",
      "versionName": "8.3.7",
      "versionDate": "2019-01-16T21:03:09.000Z",
      "versionDescription": "【详情页优化】房产小区与景点信息更丰富；\n【智能语音助手】新增景点类问答能力；\n【长途跨城方案】支持查询城市间的火车换乘方案；\n【公交支付】支持使用乘车码扫码乘车；\n【定制公交地图】优化公交地图信息，线路换乘更清晰。",
      "createTime": "2022-04-17T15:13:12.283Z",
      "updateTime": "2022-04-17T15:13:12.283Z",
      "_hasReleaseinfo": true,
      "_isExpand": false
    },
    {
      "id": 31971755,
      "country": "cn",
      "trackId": 481623196,
      "versionId": "828720252",
      "versionName": "8.7.0",
      "versionDate": "2019-06-06T23:47:13.000Z",
      "versionDescription": "性能全面升级  启动更快更流畅；\n全新3D室内图  逛街找店不迷路；\n路线规划更迅捷  减少等待秒出行；\n精选酒店安心订 价格口碑随时查；\n景点信息丰富 旅游出行更省心。",
      "createTime": "2022-04-17T15:13:12.283Z",
      "updateTime": "2022-04-17T15:13:12.283Z",
      "_hasReleaseinfo": true,
      "_isExpand": false
    },
    {
      "id": 31971756,
      "country": "cn",
      "trackId": 481623196,
      "versionId": "828720252",
      "versionName": "8.6.2",
      "versionDate": "2019-05-01T16:30:34.000Z",
      "versionDescription": "关爱专职司机，劳动节导航送现金\n景点信息更丰富，五一出行更省心\n实时推荐精准路线，躲避拥堵更快捷\n语音输入解放双手，贴心服务开口即达\n完美支持CarPlay，一键投屏车载导航",
      "createTime": "2022-04-17T15:13:12.284Z",
      "updateTime": "2022-04-17T15:13:12.284Z",
      "_hasReleaseinfo": true,
      "_isExpand": false
    },
    {
      "id": 31971757,
      "country": "cn",
      "trackId": 481623196,
      "versionId": "828720252",
      "versionName": "8.5.0",
      "versionDate": "2019-04-03T01:04:33.000Z",
      "versionDescription": "【完美支持CarPlay】一键投屏车载导航\n【支持Siri捷径】呼唤Siri，回家上班更方便\n【赏花地图】清明踏青去哪里 地图带你来赏花\n【景点信息丰富】新增游玩攻略、运营时间 旅游出行更省心\n【电子眼数据更新】覆盖全国全部类型电子眼\n【搜索查限行】限行信息随时查 春游畅快出行",
      "createTime": "2022-04-17T15:13:12.284Z",
      "updateTime": "2022-04-17T15:13:12.284Z",
      "_hasReleaseinfo": true,
      "_isExpand": false
    },
    {
      "id": 31971758,
      "country": "cn",
      "trackId": 481623196,
      "versionId": "828720252",
      "versionName": "8.9.3",
      "versionDate": "2019-10-08T23:46:25.000Z",
      "versionDescription": "【本次更新】 \n修复 iOS 13 CarPlay 在后台无法开始导航的问题\n\n【最近更新】 \n性能全面升级，启动更快体验更流畅\n全新导航视觉，重要信息更醒目操作便捷更安全\n城市页卡贴心上线，本地吃喝玩乐全攻略一键开启",
      "createTime": "2022-04-17T15:13:12.284Z",
      "updateTime": "2022-04-17T15:13:12.284Z",
      "_hasReleaseinfo": true,
      "_isExpand": false
    },
    {
      "id": 31971759,
      "country": "cn",
      "trackId": 481623196,
      "versionId": "828720252",
      "versionName": "8.1.0",
      "versionDate": "2018-09-26T21:32:31.000Z",
      "versionDescription": "【实时公交】实时查看公交到站信息，等车不着急；\n【3D地图】还原最真实的世界，支持20个城市的3D地图效果；\n【智能语音助手】语音助手更智能，说『叮当叮当』，贴心服务开口即达；\n【智能导航】智能调整诱导播报，导航指引更及时准确。",
      "createTime": "2022-04-17T15:13:12.284Z",
      "updateTime": "2022-04-17T15:13:12.284Z",
      "_hasReleaseinfo": true,
      "_isExpand": false
    },
    {
      "id": 31971760,
      "country": "cn",
      "trackId": 481623196,
      "versionId": "828665490",
      "versionName": "8.0.1",
      "versionDate": "2018-09-20T14:57:22.000Z",
      "versionDescription": "【智能语音助手】智能语音助手全新上线，说『叮当叮当』，随时召唤你的靠谱贴心的智能伙伴；\n【智能调度】智能调整播报策略，导航播报更及时准确；\n【个人中心】个人中心大改版，常用功能更清晰；\n【视觉升级】视觉翻新效果升级，指引清晰界面更清爽。",
      "createTime": "2022-04-17T15:13:12.284Z",
      "updateTime": "2022-04-17T15:13:12.284Z",
      "_hasReleaseinfo": true,
      "_isExpand": false
    },
    {
      "id": 31971761,
      "country": "cn",
      "trackId": 481623196,
      "versionId": "828461872",
      "versionName": "8.0.0",
      "versionDate": "2018-09-13T14:43:03.000Z",
      "versionDescription": "【智能语音助手】智能语音助手全新上线，说『叮当叮当』，随时召唤你的靠谱贴心的智能伙伴；\n【智能调度】智能调整播报策略，导航播报更及时准确；\n【个人中心】个人中心大改版，常用功能更清晰；\n【视觉升级】视觉翻新效果升级，指引清晰界面更清爽。",
      "createTime": "2022-04-17T15:13:12.284Z",
      "updateTime": "2022-04-17T15:13:12.284Z",
      "_hasReleaseinfo": true,
      "_isExpand": false
    },
    {
      "id": 31971762,
      "country": "cn",
      "trackId": 481623196,
      "versionId": "828316472",
      "versionName": "7.9.10",
      "versionDate": "2018-08-30T12:51:42.000Z",
      "versionDescription": "-播报智能调度，信息更完整时机更准确；\n-公交方案可缓存，路线随心查更方便；\n-实时公交上线，到站信息方便看。",
      "createTime": "2022-04-17T15:13:12.284Z",
      "updateTime": "2022-04-17T15:13:12.284Z",
      "_hasReleaseinfo": true,
      "_isExpand": false
    },
    {
      "id": 31971763,
      "country": "cn",
      "trackId": 481623196,
      "versionId": "828190682",
      "versionName": "7.9.9",
      "versionDate": "2018-08-10T15:34:07.000Z",
      "versionDescription": "-播报智能调度，信息更完整时机更准确；\n-公交方案可缓存，路线随心查更方便；\n-实时公交上线，到站信息方便看。",
      "createTime": "2022-04-17T15:13:12.284Z",
      "updateTime": "2022-04-17T15:13:12.284Z",
      "_hasReleaseinfo": true,
      "_isExpand": false
    },
    {
      "id": 31971764,
      "country": "cn",
      "trackId": 481623196,
      "versionId": "827950962",
      "versionName": "7.9.8",
      "versionDate": "2018-07-30T23:30:00.000Z",
      "versionDescription": "-实时公交上线，到站信息方便看；\n-驾车多路线导航，躲避拥堵更快捷；\n-公交详情页改版，路线信息一目了然；\n-新增影院选座服务，手指一动轻松购票。",
      "createTime": "2022-04-17T15:13:12.284Z",
      "updateTime": "2022-04-17T15:13:12.284Z",
      "_hasReleaseinfo": true,
      "_isExpand": false
    },
    {
      "id": 31971765,
      "country": "cn",
      "trackId": 481623196,
      "versionId": "827895066",
      "versionName": "7.9.7",
      "versionDate": "2018-07-17T01:40:07.000Z",
      "versionDescription": "-实时公交上线，到站信息方便看；\n-驾车多路线导航，躲避拥堵更快捷；\n-公交详情页改版，路线信息一目了然；\n-新增影院选座服务，手指一动轻松购票。",
      "createTime": "2022-04-17T15:13:12.284Z",
      "updateTime": "2022-04-17T15:13:12.284Z",
      "_hasReleaseinfo": true,
      "_isExpand": false
    },
    {
      "id": 31971766,
      "country": "cn",
      "trackId": 481623196,
      "versionId": "827831657",
      "versionName": "7.9.5",
      "versionDate": "2018-07-11T01:10:52.000Z",
      "versionDescription": "-实时公交上线，到站信息方便看；\n-驾车多路线导航，躲避拥堵更快捷；\n-公交详情页改版，路线信息一目了然；\n-新增影院选座服务，手指一动轻松购票。",
      "createTime": "2022-04-17T15:13:12.284Z",
      "updateTime": "2022-04-17T15:13:12.284Z",
      "_hasReleaseinfo": true,
      "_isExpand": false
    },
    {
      "id": 31971767,
      "country": "cn",
      "trackId": 481623196,
      "versionId": "827671779",
      "versionName": "7.9.1",
      "versionDate": "2018-06-28T02:07:39.000Z",
      "versionDescription": "-驾车多路线导航，躲避拥堵更快捷；\n-公交详情页改版，路线信息一目了然；\n-世界杯活动上线，现金红包大派送；\n-新增影院选座服务，手指一动轻松购票。",
      "createTime": "2022-04-17T15:13:12.284Z",
      "updateTime": "2022-04-17T15:13:12.284Z",
      "_hasReleaseinfo": true,
      "_isExpand": false
    },
    {
      "id": 31971768,
      "country": "cn",
      "trackId": 481623196,
      "versionId": "827540572",
      "versionName": "7.9.0",
      "versionDate": "2018-06-17T14:54:25.000Z",
      "versionDescription": "-驾车多路线导航，躲避拥堵更快捷；\n-公交详情页改版，路线信息一目了然；\n-世界杯活动上线，现金红包大派送；\n-新增影院选座服务，手指一动轻松购票。",
      "createTime": "2022-04-17T15:13:12.284Z",
      "updateTime": "2022-04-17T15:13:12.284Z",
      "_hasReleaseinfo": true,
      "_isExpand": false
    },
    {
      "id": 31971769,
      "country": "cn",
      "trackId": 481623196,
      "versionId": "827406771",
      "versionName": "7.8.0",
      "versionDate": "2018-06-09T06:03:07.000Z",
      "versionDescription": "-公交体验全面升级，出行更省心；\n-路口放大图升级，清晰呈现复杂道路；\n-景区手绘地图上线，原来地图可以这么美；\n-公交导航增步行入口，跟我走省心又省力。",
      "createTime": "2022-04-17T15:13:12.284Z",
      "updateTime": "2022-04-17T15:13:12.284Z",
      "_hasReleaseinfo": true,
      "_isExpand": false
    },
    {
      "id": 31971770,
      "country": "cn",
      "trackId": 481623196,
      "versionId": "827230421",
      "versionName": "7.7.1",
      "versionDate": "2018-05-22T01:58:01.000Z",
      "versionDescription": "-路口放大图更新，清晰呈现复杂道路；\n-公交方案页焕新，轻松掌握出行信息；\n-沿途搜功能升级，加油站充电站一目了然；\n-公交导航新增步行入口，跟我走省心又省力；\n-云南景区手绘地图上线，原来地图可以这么美。",
      "createTime": "2022-04-17T15:13:12.284Z",
      "updateTime": "2022-04-17T15:13:12.284Z",
      "_hasReleaseinfo": true,
      "_isExpand": false
    },
    {
      "id": 31971771,
      "country": "cn",
      "trackId": 481623196,
      "versionId": "827190200",
      "versionName": "7.7.0",
      "versionDate": "2018-05-18T01:14:36.000Z",
      "versionDescription": "-路口放大图更新，清晰呈现复杂道路；\n-公交方案页焕新，轻松掌握出行信息；\n-沿途搜功能升级，加油站充电站一目了然；\n-公交导航新增步行入口，跟我走省心又省力；\n-云南景区手绘地图上线，原来地图可以这么美。",
      "createTime": "2022-04-17T15:13:12.284Z",
      "updateTime": "2022-04-17T15:13:12.284Z",
      "_hasReleaseinfo": true,
      "_isExpand": false
    },
    {
      "id": 31971772,
      "country": "cn",
      "trackId": 481623196,
      "versionId": "826830696",
      "versionName": "7.6.0",
      "versionDate": "2018-04-26T15:58:06.000Z",
      "versionDescription": "-【导航】路口放大图优化改版，体验更直观路口不犹豫；\n-【沿途搜】沿途搜功能升级，加油站充电站一目了然；\n-【公交】公交导航新增步行入口，跟我走省心又省力；\n-【底图】云南景区手绘地图上线，原来地图可以这么美；\n-【活动】五一出行就用腾讯地图，互助拿红包堵车不堵心。",
      "createTime": "2022-04-17T15:13:12.284Z",
      "updateTime": "2022-04-17T15:13:12.284Z",
      "_hasReleaseinfo": true,
      "_isExpand": false
    },
    {
      "id": 31971773,
      "country": "cn",
      "trackId": 481623196,
      "versionId": "826748835",
      "versionName": "7.5.7",
      "versionDate": "2018-04-20T01:26:16.000Z",
      "versionDescription": "-沿途搜功能升级，加油站充电站一目了然；\n-公交导航新增步行入口，跟我走省心又省力；\n-路口放大图优化改版，体验更直观路口不犹豫。",
      "createTime": "2022-04-17T15:13:12.284Z",
      "updateTime": "2022-04-17T15:13:12.284Z",
      "_hasReleaseinfo": true,
      "_isExpand": false
    },
    {
      "id": 31971774,
      "country": "cn",
      "trackId": 481623196,
      "versionId": "826551691",
      "versionName": "7.5.6",
      "versionDate": "2018-04-08T02:42:46.000Z",
      "versionDescription": "-手绘地图上线，生动展示云南景区； \n-骑行规划更合理，春季出行好伴侣； \n-导航一键报平安，假期自驾更安心。",
      "createTime": "2022-04-17T15:13:12.284Z",
      "updateTime": "2022-04-17T15:13:12.284Z",
      "_hasReleaseinfo": true,
      "_isExpand": false
    },
    {
      "id": 31971775,
      "country": "cn",
      "trackId": 481623196,
      "versionId": "826404683",
      "versionName": "7.5.5",
      "versionDate": "2018-03-27T01:43:05.000Z",
      "versionDescription": "-新增上报入口，道路突发事件及时掌握；\n-道路搜索结果清晰展现，位置一目了然；\n-实时展示当前道路名，所在位置清晰明了；\n-超速、限速提醒更直观，再也不担心被罚；\n-新增多地高清3D地图，精细化展示道路信息。",
      "createTime": "2022-04-17T15:13:12.284Z",
      "updateTime": "2022-04-17T15:13:12.284Z",
      "_hasReleaseinfo": true,
      "_isExpand": false
    },
    {
      "id": 31971776,
      "country": "cn",
      "trackId": 481623196,
      "versionId": "826229239",
      "versionName": "7.5.2",
      "versionDate": "2018-03-09T03:47:49.000Z",
      "versionDescription": "-实时展示当前道路名，所在位置一目了然；\n-超速、限速提醒更直观，远离罚单驾驶更安全；\n-导航界面全新改版，视野更广更清晰；\n-沿途搜索上线，查找沿途设施更方便；\n-新增北京市高清3D地图，更多城市陆续增加。",
      "createTime": "2022-04-17T15:13:12.284Z",
      "updateTime": "2022-04-17T15:13:12.284Z",
      "_hasReleaseinfo": true,
      "_isExpand": false
    },
    {
      "id": 31971777,
      "country": "cn",
      "trackId": 481623196,
      "versionId": "825933055",
      "versionName": "7.5.1",
      "versionDate": "2018-02-09T02:04:45.000Z",
      "versionDescription": "-导航界面全新改版，视野更广更清晰；\n-新增长途导航模式，长途旅行更贴心；\n-沿途搜索上线，查找沿途设施更方便；\n-导航报平安，旅途不孤单，家人更心安；\n-新增北京市高清3D地图，更多城市陆续增加；\n-春节活动即将开启，天天有惊喜，福利享不停。",
      "createTime": "2022-04-17T15:13:12.284Z",
      "updateTime": "2022-04-17T15:13:12.284Z",
      "_hasReleaseinfo": true,
      "_isExpand": false
    },
    {
      "id": 31971778,
      "country": "cn",
      "trackId": 481623196,
      "versionId": "825890842",
      "versionName": "7.5.0",
      "versionDate": "2018-02-06T00:21:40.000Z",
      "versionDescription": "-导航界面全新改版，视野更广更清晰；\n-新增长途导航模式，长途旅行更贴心；\n-沿途搜索上线，查找沿途设施更方便；\n-导航报平安，旅途不孤单，家人更心安；\n-新增北京市高清3D地图，更多城市陆续增加；\n-春节活动即将开启，天天有惊喜，福利享不停。",
      "createTime": "2022-04-17T15:13:12.284Z",
      "updateTime": "2022-04-17T15:13:12.284Z",
      "_hasReleaseinfo": true,
      "_isExpand": false
    },
    {
      "id": 31971779,
      "country": "cn",
      "trackId": 481623196,
      "versionId": "825670264",
      "versionName": "7.4.5",
      "versionDate": "2018-01-23T02:08:10.000Z",
      "versionDescription": "-停车场增加实时数据，找车位如此简单；\n-新增北京市高清3D地图，更多城市陆续增加；\n-探索附近全新升级，人气去处一网打尽；\n-导航结果页优化改版，路线路况快捷反馈；\n-小区增加周边推荐地点，便利生活一键开启。",
      "createTime": "2022-04-17T15:13:12.284Z",
      "updateTime": "2022-04-17T15:13:12.284Z",
      "_hasReleaseinfo": true,
      "_isExpand": false
    },
    {
      "id": 31971780,
      "country": "cn",
      "trackId": 481623196,
      "versionId": "825466734",
      "versionName": "7.4.0",
      "versionDate": "2017-12-29T01:26:18.000Z",
      "versionDescription": "-探索附近全新升级，人气去处一网打尽；\n-导航结果页优化改版，路线路况快捷反馈；\n-小区增加周边推荐地点，便利生活一键开启；\n-步行、骑行地图丰富沿途参照物，不再迷路；\n-智能规避限行，海量数据保证，限行不再烦恼。",
      "createTime": "2022-04-17T15:13:12.284Z",
      "updateTime": "2022-04-17T15:13:12.284Z",
      "_hasReleaseinfo": true,
      "_isExpand": false
    },
    {
      "id": 31971781,
      "country": "cn",
      "trackId": 481623196,
      "versionId": "825357817",
      "versionName": "7.3.0",
      "versionDate": "2017-12-19T03:06:43.000Z",
      "versionDescription": "-小区增加周边推荐地点，便利生活一键开启；\n-步行、骑行地图丰富沿途参照物，不再迷路；\n-公交导航全面进化，省时、省力更贴心；\n-智能规避限行，海量数据保证，限行不再烦恼；\n-电子眼智能优化，新增10万+数据，从此告别罚单",
      "createTime": "2022-04-17T15:13:12.284Z",
      "updateTime": "2022-04-17T15:13:12.284Z",
      "_hasReleaseinfo": true,
      "_isExpand": false
    },
    {
      "id": 31971782,
      "country": "cn",
      "trackId": 481623196,
      "versionId": "825140484",
      "versionName": "7.2.0",
      "versionDate": "2017-12-04T22:23:39.000Z",
      "versionDescription": "-公交导航全面升级，省时、省力更贴心；\n-智能规避限行，海量数据保证，限行不再烦恼；\n-李白妲己为您导航，王者荣耀人气英雄伴你同行；\n-电子眼智能优化，新增10万+数据，从此告别罚单；\n-常用地址推荐，智能判断常用地点，搜索路线更方便；",
      "createTime": "2022-04-17T15:13:12.284Z",
      "updateTime": "2022-04-17T15:13:12.284Z",
      "_hasReleaseinfo": true,
      "_isExpand": false
    },
    {
      "id": 31971783,
      "country": "cn",
      "trackId": 481623196,
      "versionId": "824642351",
      "versionName": "7.1.0",
      "versionDate": "2017-11-21T00:40:51.000Z",
      "versionDescription": "-李白导航语音上线，王者荣耀帅气小哥伴你同行；\n-限速提醒、电子狗功能优化，告别超速和罚单；\n-常用地点功能优化：回家去公司，一键直达；\n-安装包大幅瘦身，关爱你的手机内存；\n-整体界面改版，使用更快捷高效；",
      "createTime": "2022-04-17T15:13:12.284Z",
      "updateTime": "2022-04-17T15:13:12.284Z",
      "_hasReleaseinfo": true,
      "_isExpand": false
    },
    {
      "id": 31971784,
      "country": "cn",
      "trackId": 481623196,
      "versionId": "824434036",
      "versionName": "7.0.4",
      "versionDate": "2017-11-17T02:49:39.000Z",
      "versionDescription": "-性能更优：启动快、响应快，操作更流畅；\n-导航限速提醒、电子狗功能优化上线,从此告别超速和罚单；\n-常用地点“家和公司”功能优化：回家去公司，一键直达；\n-妲己语音导航：王者荣耀官方授权，小妲己为你贴心导航；\n-安装包大幅瘦身：最小的手机地图，关爱你的手机内存；\n-整体界面改版：操作流程简化，使用更快捷高效；\n-呈现更清晰：底图层次分明，信息呈现清晰明了；",
      "createTime": "2022-04-17T15:13:12.284Z",
      "updateTime": "2022-04-17T15:13:12.284Z",
      "_hasReleaseinfo": true,
      "_isExpand": false
    },
    {
      "id": 31971785,
      "country": "cn",
      "trackId": 481623196,
      "versionId": "824268543",
      "versionName": "7.0.3",
      "versionDate": "2017-11-04T02:18:12.000Z",
      "versionDescription": "-性能更优：启动快、响应快，操作更流畅；\n-导航限速提醒、电子狗功能优化上线,从此告别超速和罚单；\n-常用地点“家和公司”功能优化：回家去公司，一键直达；\n-妲己语音导航：王者荣耀官方授权，小妲己为你贴心导航；\n-安装包大幅瘦身：最小的手机地图，关爱你的手机内存；\n-整体界面改版：操作流程简化，使用更快捷高效；\n-呈现更清晰：底图层次分明，信息呈现清晰明了；",
      "createTime": "2022-04-17T15:13:12.284Z",
      "updateTime": "2022-04-17T15:13:12.284Z",
      "_hasReleaseinfo": true,
      "_isExpand": false
    },
    {
      "id": 31971786,
      "country": "cn",
      "trackId": 481623196,
      "versionId": "824161876",
      "versionName": "7.0.2",
      "versionDate": "2017-10-28T02:24:16.000Z",
      "versionDescription": "-导航限速提醒、电子狗功能优化上线：从此告别超速和罚单；\n-常用地点“家和公司”功能优化：回家去公司，一键直达；\n-妲己语音导航：王者荣耀官方授权，小妲己为你贴心导航；\n-安装包大幅瘦身：最小的手机地图，关爱你的手机内存；\n-整体界面改版：操作流程简化，使用更快捷高效；\n-性能更优：启动快、响应快，操作更流畅；\n-呈现更清晰：底图层次分明，信息呈现清晰明了；",
      "createTime": "2022-04-17T15:13:12.284Z",
      "updateTime": "2022-04-17T15:13:12.284Z",
      "_hasReleaseinfo": true,
      "_isExpand": false
    },
    {
      "id": 31971787,
      "country": "cn",
      "trackId": 481623196,
      "versionId": "823827781",
      "versionName": "7.0.1",
      "versionDate": "2017-09-29T20:24:41.000Z",
      "versionDescription": "-妲己语音导航：王者荣耀官方授权，妲己语音为您精准导航\n-安装包大幅瘦身：安装包最小的手机地图，关爱您的手机内存；\n-整体界面改版：操作流程简化，使用更快捷高效；\n-性能更优：APP启动快、响应快，操作更流畅；\n-呈现更清晰：底图层次分明，信息呈现清晰明了；\n-修复已知bug，运行更顺畅；",
      "createTime": "2022-04-17T15:13:12.284Z",
      "updateTime": "2022-04-17T15:13:12.284Z",
      "_hasReleaseinfo": true,
      "_isExpand": false
    },
    {
      "id": 31971788,
      "country": "cn",
      "trackId": 481623196,
      "versionId": "823628987",
      "versionName": "7.0.0",
      "versionDate": "2017-09-14T06:49:51.000Z",
      "versionDescription": "【新功能部分】\n【亮点功能】\n-妲己语音导航：王者荣耀官方授权，小妲己为你贴心导航；\n-安装包大幅瘦身：最小的手机地图，关爱你的手机内存；\n-整体界面改版：操作流程简化，使用更快捷高效；\n【优化功能】\n-性能更优：启动快、响应快，操作更流畅；\n-呈现更清晰：底图层次分明，信息呈现清晰明了；",
      "createTime": "2022-04-17T15:13:12.284Z",
      "updateTime": "2022-04-17T15:13:12.284Z",
      "_hasReleaseinfo": true,
      "_isExpand": false
    },
    {
      "id": 31971789,
      "country": "cn",
      "trackId": 481623196,
      "versionId": "822972761",
      "versionName": "6.9.5",
      "versionDate": "2017-07-22T02:08:46.000Z",
      "versionDescription": "【新增功能】\n-语音播报优化：播报更清晰，导航更精准\n【全新数据】\n-违章高发地：更新东莞，南京，青岛，沈阳等26个城市的违章高发地提醒；\n-实景电子眼：更新武汉，长沙，广州，重庆等14个城市的电子眼实景图；",
      "createTime": "2022-04-17T15:13:12.284Z",
      "updateTime": "2022-04-17T15:13:12.284Z",
      "_hasReleaseinfo": true,
      "_isExpand": false
    },
    {
      "id": 31971790,
      "country": "cn",
      "trackId": 481623196,
      "versionId": "822623013",
      "versionName": "6.9.0",
      "versionDate": "2017-06-20T17:04:34.000Z",
      "versionDescription": "【新增功能】\n-语音播报优化：播报更清晰，导航更精准\n【全新数据】\n-违章高发地：更新东莞，南京，青岛，沈阳等26个城市的违章高发地提醒；\n-实景电子眼：更新武汉，长沙，广州，重庆等14个城市的电子眼实景图；",
      "createTime": "2022-04-17T15:13:12.284Z",
      "updateTime": "2022-04-17T15:13:12.284Z",
      "_hasReleaseinfo": true,
      "_isExpand": false
    },
    {
      "id": 31971791,
      "country": "cn",
      "trackId": 481623196,
      "versionId": "822110255",
      "versionName": "6.8.0",
      "versionDate": "2017-05-11T17:29:19.000Z",
      "versionDescription": "-方言语音包上线：亲切家乡话 导航更舒心\n-导航页面再升级：道路信息更突显 驾车指示更明确\n【全新数据】\n-违章高发地：更新长沙、广州、重庆、东莞等26个城市的违章高发地提醒；\n-实景电子眼：更新北京、济南、天津、深圳等14个城市的电子眼实景图；",
      "createTime": "2022-04-17T15:13:12.284Z",
      "updateTime": "2022-04-17T15:13:12.284Z",
      "_hasReleaseinfo": true,
      "_isExpand": false
    },
    {
      "id": 31971792,
      "country": "cn",
      "trackId": 481623196,
      "versionId": "821649683",
      "versionName": "6.7.5",
      "versionDate": "2017-04-06T17:38:16.000Z",
      "versionDescription": "【新增功能】\n-骑行导航全新上线：骑车出行有规划 专用路线更安全\n-路线探测躲拥堵：熟悉路线更顺畅 通勤更轻松\n-修复已知bug，运行更顺畅\n【全新数据】\n-违章高发地：更新长沙、广州、重庆、东莞等26个城市的违章高发地提醒；\n-实景电子眼：更新北京、济南、天津、深圳等14个城市的电子眼实景图；",
      "createTime": "2022-04-17T15:13:12.284Z",
      "updateTime": "2022-04-17T15:13:12.284Z",
      "_hasReleaseinfo": true,
      "_isExpand": false
    },
    {
      "id": 31971793,
      "country": "cn",
      "trackId": 481623196,
      "versionId": "821573626",
      "versionName": "6.7.0",
      "versionDate": "2017-04-03T23:01:42.000Z",
      "versionDescription": "-骑行导航全新上线：骑车出行有规划 专用路线更安全\n-路线探测躲拥堵：熟悉路线更顺畅 通勤更轻松\n【全新数据】\n-违章高发地：更新长沙、广州、重庆、东莞等26个城市的违章高发地提醒；\n-实景电子眼：更新北京、济南、天津、深圳等14个城市的电子眼实景图；",
      "createTime": "2022-04-17T15:13:12.284Z",
      "updateTime": "2022-04-17T15:13:12.284Z",
      "_hasReleaseinfo": true,
      "_isExpand": false
    },
    {
      "id": 31971794,
      "country": "cn",
      "trackId": 481623196,
      "versionId": "821143943",
      "versionName": "6.6.0",
      "versionDate": "2017-03-01T17:39:15.000Z",
      "versionDescription": "【新增功能】\n-驾车地图全新优化：驾车路线更突显 道路层次更分明\n-复杂岔口提示升级：岔口提示更明确 不再走错路\n【全新数据】\n-违章高发地：更新长沙、广州、重庆、东莞等26个城市的违章高发地提醒；\n-实景电子眼：更新北京、成都、青岛、大连等28个城市的电子眼实景图；",
      "createTime": "2022-04-17T15:13:12.284Z",
      "updateTime": "2022-04-17T15:13:12.284Z",
      "_hasReleaseinfo": true,
      "_isExpand": false
    },
    {
      "id": 31971795,
      "country": "cn",
      "trackId": 481623196,
      "versionId": "820606967",
      "versionName": "6.5.1",
      "versionDate": "2017-01-18T17:32:59.000Z",
      "versionDescription": "【新增功能】\n-新增地铁图：地铁线路、换乘方案更清晰\n-界面布局精简：视觉清爽 功能使用更便捷\n-好友同行创意玩法：涂鸦指路+春节福袋 玩转地图\n-隧道岔口提前报：隧道路况先知道 不怕没信号\n-修复已知Bug\n【全新数据】\n-违章高发地：新增开封、南平、平顶山、濮阳等8个城市的违章高发地提醒；\n-实景电子眼：新增常州、佛山、金华、常州等8个城市的电子眼实景图；",
      "createTime": "2022-04-17T15:13:12.284Z",
      "updateTime": "2022-04-17T15:13:12.284Z",
      "_hasReleaseinfo": true,
      "_isExpand": false
    },
    {
      "id": 31971796,
      "country": "cn",
      "trackId": 481623196,
      "versionId": "820541021",
      "versionName": "6.5.0",
      "versionDate": "2017-01-13T19:10:42.000Z",
      "versionDescription": "【新增功能】\n-新增地铁图：地铁线路、换乘方案更清晰\n-界面布局精简：视觉清爽 功能使用更便捷\n-好友同行创意玩法：涂鸦指路+春节福袋 玩转地图\n-隧道岔口提前报：隧道路况先知道 不怕没信号\n【全新数据】\n-违章高发地：新增开封、南平、平顶山、濮阳等8个城市的违章高发地提醒；\n-实景电子眼：新增常州、佛山、金华、常州等8个城市的电子眼实景图；",
      "createTime": "2022-04-17T15:13:12.284Z",
      "updateTime": "2022-04-17T15:13:12.284Z",
      "_hasReleaseinfo": true,
      "_isExpand": false
    },
    {
      "id": 31971797,
      "country": "cn",
      "trackId": 481623196,
      "versionId": "820358635",
      "versionName": "6.4.5",
      "versionDate": "2017-01-02T18:33:02.000Z",
      "versionDescription": "【新增功能】\n-新增封闭路段展示：封路信息一目了然，不怕走错路\n-拥堵时间、距离提示：预估拥堵时间，路遇堵车早决策\n-修复已知bug，界面更清晰美观\n【独家数据】\n-违章高发地：新增岳阳、云浮、自贡、资阳等22个城市的违章高发地提醒；\n-实景电子眼：新增嘉兴、清远、常州、抚州等8个城市的电子眼实景图；",
      "createTime": "2022-04-17T15:13:12.284Z",
      "updateTime": "2022-04-17T15:13:12.284Z",
      "_hasReleaseinfo": true,
      "_isExpand": false
    },
    {
      "id": 31971798,
      "country": "cn",
      "trackId": 481623196,
      "versionId": "820176257",
      "versionName": "6.4.0",
      "versionDate": "2016-12-15T17:18:53.000Z",
      "versionDescription": "【新增功能】\n-新增封闭路段展示：封路信息一目了然，不怕走错路\n-拥堵时间、距离提示：预估拥堵时间，路遇堵车早决策\n【独家数据】\n-违章高发地：新增岳阳、云浮、自贡、资阳等22个城市的违章高发地提醒；\n-实景电子眼：新增嘉兴、清远、常州、抚州等8个城市的电子眼实景图；",
      "createTime": "2022-04-17T15:13:12.284Z",
      "updateTime": "2022-04-17T15:13:12.284Z",
      "_hasReleaseinfo": true,
      "_isExpand": false
    },
    {
      "id": 31971799,
      "country": "cn",
      "trackId": 481623196,
      "versionId": "819887042",
      "versionName": "6.3.5",
      "versionDate": "2016-11-30T17:37:12.000Z",
      "versionDescription": "【新增功能】\n-导航可以攒积分换礼品啦，车友们快更新试试吧！\n【数据更新】\n-违章高发地：新增安庆、宝鸡、常德等25个城市的违章高发地提醒；\n-实景电子眼：新增吕梁、辽阳等2个城市的电子眼实景图；",
      "createTime": "2022-04-17T15:13:12.284Z",
      "updateTime": "2022-04-17T15:13:12.284Z",
      "_hasReleaseinfo": true,
      "_isExpand": false
    },
    {
      "id": 31971800,
      "country": "cn",
      "trackId": 481623196,
      "versionId": "819753041",
      "versionName": "6.3.0",
      "versionDate": "2016-11-16T18:35:11.000Z",
      "versionDescription": "【新增功能】\n-更聪明的语音导航，车友们快更新试试吧！\n【独家数据】\n-违章高发地：新增安庆、宝鸡、常德等25个城市的违章高发地提醒；\n-实景电子眼：新增吕梁、辽阳等2个城市的电子眼实景图；",
      "createTime": "2022-04-17T15:13:12.284Z",
      "updateTime": "2022-04-17T15:13:12.284Z",
      "_hasReleaseinfo": true,
      "_isExpand": false
    },
    {
      "id": 31971801,
      "country": "cn",
      "trackId": 481623196,
      "versionId": "819110251",
      "versionName": "6.2.1",
      "versionDate": "2016-10-03T12:22:15.000Z",
      "versionDescription": "【新增功能】\n-导航语音播报优化，贴心播报一路伴随，驾驶更省心；\n-常用地址设置更便捷，通勤路况一目了然；\n-修复已知bug，运行更顺畅！\n【独家数据】\n-违章高发地：新增抚州、牡丹江、南充、泸州、眉山、内江等6个城市的违章高发地提醒；\n-实景电子眼：新增达州、怀化、汕尾、通化、新余、自贡、赤峰等21个城市的电子眼实景图；",
      "createTime": "2022-04-17T15:13:12.284Z",
      "updateTime": "2022-04-17T15:13:12.284Z",
      "_hasReleaseinfo": true,
      "_isExpand": false
    },
    {
      "id": 31971802,
      "country": "cn",
      "trackId": 481623196,
      "versionId": "819029221",
      "versionName": "6.2.0",
      "versionDate": "2016-09-23T22:11:43.000Z",
      "versionDescription": "【新增功能】\n-导航语音播报优化，贴心播报一路伴随，驾驶更省心；\n-常用地址设置更便捷，通勤路况一目了然；\n【独家数据】\n-违章高发地：新增抚州、牡丹江、南充、泸州、眉山、内江等6个城市的违章高发地提醒；\n-实景电子眼：新增达州、怀化、汕尾、通化、新余、自贡、赤峰等21个城市的电子眼实景图；",
      "createTime": "2022-04-17T15:13:12.284Z",
      "updateTime": "2022-04-17T15:13:12.284Z",
      "_hasReleaseinfo": true,
      "_isExpand": false
    },
    {
      "id": 31971803,
      "country": "cn",
      "trackId": 481623196,
      "versionId": "818734948",
      "versionName": "6.1.2",
      "versionDate": "2016-09-01T19:02:30.000Z",
      "versionDescription": "【新增功能】\n-新增了服务区、加油站、出入口的提示小牌，就在导航屏幕的左上角，驾车更省心；\n-接入了海量酒店数据，选好位置直接预定~\n-高颜值产品经理小田田调整HOV车道播报策略，和罚款说byebye！\n【独家数据】\n-违章高发地：新增上饶、新乡、临汾、六安、黄山等10个城市的违章高发地提醒；\n-实景电子眼：新增呼和浩特、黄冈、南平、宜春、呼伦贝尔、三明等6个城市的电子眼实景图；",
      "createTime": "2022-04-17T15:13:12.284Z",
      "updateTime": "2022-04-17T15:13:12.284Z",
      "_hasReleaseinfo": true,
      "_isExpand": false
    },
    {
      "id": 31971804,
      "country": "cn",
      "trackId": 481623196,
      "versionId": "818665917",
      "versionName": "6.1.1",
      "versionDate": "2016-08-28T18:57:16.000Z",
      "versionDescription": "【新增功能】\n-新增了服务区、加油站、出入口的提示小牌，就在导航屏幕的左上角，驾车更省心；\n-接入了海量酒店数据，选好位置直接预定~\n-高颜值产品经理小田田调整HOV车道播报策略，和罚款说byebye！\n【独家数据】\n-违章高发地：新增上饶、新乡、临汾、六安、黄山等10个城市的违章高发地提醒；\n-实景电子眼：新增呼和浩特、黄冈、南平、宜春、呼伦贝尔、三明等6个城市的电子眼实景图；",
      "createTime": "2022-04-17T15:13:12.284Z",
      "updateTime": "2022-04-17T15:13:12.284Z",
      "_hasReleaseinfo": true,
      "_isExpand": false
    },
    {
      "id": 31971805,
      "country": "cn",
      "trackId": 481623196,
      "versionId": "818598792",
      "versionName": "6.1.0",
      "versionDate": "2016-08-25T18:33:14.000Z",
      "versionDescription": "【新增功能】\n-新增了服务区、加油站、出入口的提示小牌，就在导航屏幕的左上角，驾车更省心；\n-接入了海量酒店数据，选好位置直接预定~\n-高颜值产品经理小田田调整HOV车道播报策略，严捂钱包！\n【独家数据】\n-违章高发地：新增上饶、新乡、临汾、六安、黄山等10个城市的违章高发地提醒；\n-实景电子眼：新增呼和浩特、黄冈、南平、宜春、呼伦贝尔、三明等6个城市的电子眼实景图；",
      "createTime": "2022-04-17T15:13:12.284Z",
      "updateTime": "2022-04-17T15:13:12.284Z",
      "_hasReleaseinfo": true,
      "_isExpand": false
    },
    {
      "id": 31971806,
      "country": "cn",
      "trackId": 481623196,
      "versionId": "818272969",
      "versionName": "6.0.0",
      "versionDate": "2016-08-05T17:10:30.000Z",
      "versionDescription": "【新增功能】\n-深圳首条多乘员车道（HOV）8月1日正式运行啦，腾讯地图贴心上线电子眼播报HOV路段功能，和罚单说Byebye~\n-程序猿哥哥优化了性能，运行更顺畅！\n【独家数据】\n-违章高发地：新增许昌、舟山等2个城市的违章高发地提醒；\n-实景电子眼：新增黄山、锦州、营口、抚州、牡丹江、威海 等34个城市的电子眼实景图；",
      "createTime": "2022-04-17T15:13:12.284Z",
      "updateTime": "2022-04-17T15:13:12.284Z",
      "_hasReleaseinfo": true,
      "_isExpand": false
    },
    {
      "id": 31971807,
      "country": "cn",
      "trackId": 481623196,
      "versionId": "817867588",
      "versionName": "5.9.5",
      "versionDate": "2016-06-26T18:46:39.000Z",
      "versionDescription": "【新增功能】\n-新增语音上报：路线规划不满意？一键上报来吐槽\n【独家数据】\n-违章高发地：新增荆州、乐山、丽江、蚌埠、丽水等9个城市的违章高发地提醒；\n-实景电子眼：新增许昌、鄂尔多斯、上饶、新乡、舟山等9个城市的电子眼实景图；",
      "createTime": "2022-04-17T15:13:12.284Z",
      "updateTime": "2022-04-17T15:13:12.284Z",
      "_hasReleaseinfo": true,
      "_isExpand": false
    },
    {
      "id": 31971808,
      "country": "cn",
      "trackId": 481623196,
      "versionId": "817306214",
      "versionName": "5.9.0",
      "versionDate": "2016-05-08T18:41:02.000Z",
      "versionDescription": "【新增功能】\n-智能并线提示：语音提醒，驾车更省心，不怕走错道！\n-高架、主辅路确认：路线及时调整，导航更精确\n【独家数据】\n-违章高发地：更新莆田、宿迁、揭阳、潮州、德阳等11个城市的违章高发地提醒；\n-实景电子眼：新增江门、荆州、乐山、丽江、蚌埠等10个城市的电子眼实景图；",
      "createTime": "2022-04-17T15:13:12.284Z",
      "updateTime": "2022-04-17T15:13:12.284Z",
      "_hasReleaseinfo": true,
      "_isExpand": false
    },
    {
      "id": 31971809,
      "country": "cn",
      "trackId": 481623196,
      "versionId": "816745201",
      "versionName": "5.8",
      "versionDate": "2016-03-17T17:30:46.000Z",
      "versionDescription": "【新增功能】\n-好友聚会一同行：加入群组 实时位置一目了然 \n-趣味弹幕新玩法：好友群聊 导航吐槽两不误 \n-涂鸦地图能指路：路痴不用怕 好友涂鸦远程指导！\n【独家数据】\n-违章高发地：更新成都、泰安、嘉兴、绍兴、银川等31个城市的违章高发地提醒；\n-实景电子眼：新增揭阳、潮州、德阳、衡阳、赣州、绵阳、扬州、株洲等8个城市的电子眼实景图；",
      "createTime": "2022-04-17T15:13:12.284Z",
      "updateTime": "2022-04-17T15:13:12.284Z",
      "_hasReleaseinfo": true,
      "_isExpand": false
    },
    {
      "id": 31971810,
      "country": "cn",
      "trackId": 481623196,
      "versionId": "816745201",
      "versionName": "5.8.0",
      "versionDate": "2016-03-17T17:30:46.000Z",
      "versionDescription": "【新增功能】\n-好友聚会一同行：加入群组 实时位置一目了然 \n-趣味弹幕新玩法：好友群聊 导航吐槽两不误 \n-涂鸦地图能指路：路痴不用怕 好友涂鸦远程指导！\n【独家数据】\n-违章高发地：更新成都、泰安、嘉兴、绍兴、银川等31个城市的违章高发地提醒；\n-实景电子眼：新增揭阳、潮州、德阳、衡阳、赣州、绵阳、扬州、株洲等8个城市的电子眼实景图；",
      "createTime": "2022-04-17T15:13:12.284Z",
      "updateTime": "2022-04-17T15:13:12.284Z",
      "_hasReleaseinfo": true,
      "_isExpand": false
    },
    {
      "id": 31971811,
      "country": "cn",
      "trackId": 481623196,
      "versionId": "816288885",
      "versionName": "5.7.1",
      "versionDate": "2016-02-02T18:03:36.000Z",
      "versionDescription": "-春节主题上线：春节贺岁主题喜庆上线，祝您新春快乐，出行平安！\n-公交到站提醒：贴心到站提醒，告别过站，出行更从容；\n-室内地图功能：机场、火车站、商场室内详情尽在掌握，带您玩转春运（北京地区抢先体验）；\n-新增夜间模式：护眼模式一键切换，夜间出行不伤眼；\n-鹰眼导航助手：“当前路况+全程信息”实时知晓，从此轻松驾驶！\n【独家数据】\n-违章高发地：新增南阳、太原、漳州、湛江、河源、肇庆等6个城市的违章高发地提醒；\n-实景电子眼：新增咸阳、莆田、宿迁等3个城市的电子眼实景图；",
      "createTime": "2022-04-17T15:13:12.284Z",
      "updateTime": "2022-04-17T15:13:12.284Z",
      "_hasReleaseinfo": true,
      "_isExpand": false
    },
    {
      "id": 31971812,
      "country": "cn",
      "trackId": 481623196,
      "versionId": "816107185",
      "versionName": "5.7",
      "versionDate": "2016-01-22T00:14:02.000Z",
      "versionDescription": "【新增功能】\n-春节主题上线：春节贺岁主题喜庆上线，祝您新春快乐，出行平安！\n-公交到站提醒：贴心到站提醒，告别过站，出行更从容；\n-室内地图功能：机场、火车站、商场室内详情尽在掌握，带您玩转春运（北京地区抢先体验）；\n-新增夜间模式：护眼模式一键切换，夜间出行不伤眼；\n-鹰眼导航助手：“当前路况+全程信息”实时知晓，从此轻松驾驶！\n【独家数据】\n-违章高发地：新增南阳、太原、漳州、湛江、河源、肇庆等6个城市的违章高发地提醒；\n-实景电子眼：新增咸阳、莆田、宿迁等3个城市的电子眼实景图；",
      "createTime": "2022-04-17T15:13:12.284Z",
      "updateTime": "2022-04-17T15:13:12.284Z",
      "_hasReleaseinfo": true,
      "_isExpand": false
    },
    {
      "id": 31971813,
      "country": "cn",
      "trackId": 481623196,
      "versionId": "816107185",
      "versionName": "5.7.0",
      "versionDate": "2016-01-22T00:14:02.000Z",
      "versionDescription": "【新增功能】\n-春节主题上线：春节贺岁主题喜庆上线，祝您新春快乐，出行平安！\n-公交到站提醒：贴心到站提醒，告别过站，出行更从容；\n-室内地图功能：机场、火车站、商场室内详情尽在掌握，带您玩转春运（北京地区抢先体验）；\n-新增夜间模式：护眼模式一键切换，夜间出行不伤眼；\n-鹰眼导航助手：“当前路况+全程信息”实时知晓，从此轻松驾驶！\n【独家数据】\n-违章高发地：新增南阳、太原、漳州、湛江、河源、肇庆等6个城市的违章高发地提醒；\n-实景电子眼：新增咸阳、莆田、宿迁等3个城市的电子眼实景图；",
      "createTime": "2022-04-17T15:13:12.284Z",
      "updateTime": "2022-04-17T15:13:12.284Z",
      "_hasReleaseinfo": true,
      "_isExpand": false
    },
    {
      "id": 31971814,
      "country": "cn",
      "trackId": 481623196,
      "versionId": "815871510",
      "versionName": "5.6.8",
      "versionDate": "2016-01-13T18:46:54.000Z",
      "versionDescription": "-腾讯推出首款高级驾驶安全辅助神器——腾讯神眼\n-腾讯神眼拥有顶尖的ADAS驾驶辅助系统、超清晰的行车记录功能、超好玩的视频分享功能\n-当出现前车碰撞危险时、当出现疲劳驾驶时、当行车出现车道偏移时，神眼会及时为您发出警报\n-手机连接神眼后，可以观看行车视频、下载视频、神眼拍照、对神眼进行设置等；",
      "createTime": "2022-04-17T15:13:12.284Z",
      "updateTime": "2022-04-17T15:13:12.284Z",
      "_hasReleaseinfo": true,
      "_isExpand": false
    },
    {
      "id": 31971815,
      "country": "cn",
      "trackId": 481623196,
      "versionId": "815586394",
      "versionName": "5.6.7",
      "versionDate": "2016-01-10T06:26:05.000Z",
      "versionDescription": "-腾讯推出首款高级驾驶安全辅助神器——腾讯神眼\n-腾讯神眼拥有顶尖的ADAS驾驶辅助系统、超清晰的行车记录功能、超好玩的视频分享功能\n-当出现前车碰撞危险时、当出现疲劳驾驶时、当行车出现车道偏移时，神眼会及时为您发出警报\n-手机连接神眼后，可以观看行车视频、下载视频、神眼拍照、对神眼进行设置等；",
      "createTime": "2022-04-17T15:13:12.284Z",
      "updateTime": "2022-04-17T15:13:12.284Z",
      "_hasReleaseinfo": true,
      "_isExpand": false
    },
    {
      "id": 31971816,
      "country": "cn",
      "trackId": 481623196,
      "versionId": "815405395",
      "versionName": "5.6.6",
      "versionDate": "2015-12-17T17:25:47.000Z",
      "versionDescription": "【新增功能】\n-打车功能便捷上线：一键打车，温暖直达；更有免费打车券任性送，你打车，我给钱！\n-优化界面显示：类目清晰，个人定制信息一目了然；修复已知bug，提高运行性能\n【独家数据】\n-违章高发地：新增三亚、周口、桂林、安阳等4个城市的违章高发地提醒；\n-实景电子眼：新增安阳、湛江、漳州、河源、肇庆等5个城市的电子眼实景图；",
      "createTime": "2022-04-17T15:13:12.284Z",
      "updateTime": "2022-04-17T15:13:12.284Z",
      "_hasReleaseinfo": true,
      "_isExpand": false
    },
    {
      "id": 31971817,
      "country": "cn",
      "trackId": 481623196,
      "versionId": "814825967",
      "versionName": "5.6.3",
      "versionDate": null,
      "versionDescription": "",
      "createTime": "2022-04-17T15:13:12.284Z",
      "updateTime": "2022-04-17T15:13:12.284Z",
      "_hasReleaseinfo": false,
      "_isExpand": false
    },
    {
      "id": 31971818,
      "country": "cn",
      "trackId": 481623196,
      "versionId": "814408166",
      "versionName": "5.5.1",
      "versionDate": null,
      "versionDescription": "",
      "createTime": "2022-04-17T15:13:12.284Z",
      "updateTime": "2022-04-17T15:13:12.284Z",
      "_hasReleaseinfo": false,
      "_isExpand": false
    },
    {
      "id": 31971819,
      "country": "cn",
      "trackId": 481623196,
      "versionId": "813460480",
      "versionName": "5.4.1",
      "versionDate": null,
      "versionDescription": "",
      "createTime": "2022-04-17T15:13:12.284Z",
      "updateTime": "2022-04-17T15:13:12.284Z",
      "_hasReleaseinfo": false,
      "_isExpand": false
    },
    {
      "id": 31971820,
      "country": "cn",
      "trackId": 481623196,
      "versionId": "812852722",
      "versionName": "5.2.0",
      "versionDate": null,
      "versionDescription": "",
      "createTime": "2022-04-17T15:13:12.284Z",
      "updateTime": "2022-04-17T15:13:12.284Z",
      "_hasReleaseinfo": false,
      "_isExpand": false
    },
    {
      "id": 31971821,
      "country": "cn",
      "trackId": 481623196,
      "versionId": "812514710",
      "versionName": "5.1.0",
      "versionDate": null,
      "versionDescription": "",
      "createTime": "2022-04-17T15:13:12.284Z",
      "updateTime": "2022-04-17T15:13:12.284Z",
      "_hasReleaseinfo": false,
      "_isExpand": false
    },
    {
      "id": 31971822,
      "country": "cn",
      "trackId": 481623196,
      "versionId": "812140793",
      "versionName": "5.0.1",
      "versionDate": null,
      "versionDescription": "",
      "createTime": "2022-04-17T15:13:12.284Z",
      "updateTime": "2022-04-17T15:13:12.284Z",
      "_hasReleaseinfo": false,
      "_isExpand": false
    },
    {
      "id": 31971823,
      "country": "cn",
      "trackId": 481623196,
      "versionId": "812039204",
      "versionName": "4.9.6",
      "versionDate": null,
      "versionDescription": "",
      "createTime": "2022-04-17T15:13:12.284Z",
      "updateTime": "2022-04-17T15:13:12.284Z",
      "_hasReleaseinfo": false,
      "_isExpand": false
    },
    {
      "id": 31971824,
      "country": "cn",
      "trackId": 481623196,
      "versionId": "811789507",
      "versionName": "4.9.1",
      "versionDate": null,
      "versionDescription": "",
      "createTime": "2022-04-17T15:13:12.284Z",
      "updateTime": "2022-04-17T15:13:12.284Z",
      "_hasReleaseinfo": false,
      "_isExpand": false
    },
    {
      "id": 31971825,
      "country": "cn",
      "trackId": 481623196,
      "versionId": "693142667",
      "versionName": "4.5.1",
      "versionDate": null,
      "versionDescription": "",
      "createTime": "2022-04-17T15:13:12.284Z",
      "updateTime": "2022-04-17T15:13:12.284Z",
      "_hasReleaseinfo": false,
      "_isExpand": false
    },
    {
      "id": 31971826,
      "country": "cn",
      "trackId": 481623196,
      "versionId": "659202968",
      "versionName": "4.5",
      "versionDate": null,
      "versionDescription": "",
      "createTime": "2022-04-17T15:13:12.284Z",
      "updateTime": "2022-04-17T15:13:12.284Z",
      "_hasReleaseinfo": false,
      "_isExpand": false
    },
    {
      "id": 31971827,
      "country": "cn",
      "trackId": 481623196,
      "versionId": "610162713",
      "versionName": "4.4",
      "versionDate": null,
      "versionDescription": "",
      "createTime": "2022-04-17T15:13:12.284Z",
      "updateTime": "2022-04-17T15:13:12.284Z",
      "_hasReleaseinfo": false,
      "_isExpand": false
    },
    {
      "id": 31971828,
      "country": "cn",
      "trackId": 481623196,
      "versionId": "591153024",
      "versionName": "4.3.1",
      "versionDate": null,
      "versionDescription": "",
      "createTime": "2022-04-17T15:13:12.284Z",
      "updateTime": "2022-04-17T15:13:12.284Z",
      "_hasReleaseinfo": false,
      "_isExpand": false
    },
    {
      "id": 31971829,
      "country": "cn",
      "trackId": 481623196,
      "versionId": "536572632",
      "versionName": "4.2",
      "versionDate": null,
      "versionDescription": "",
      "createTime": "2022-04-17T15:13:12.284Z",
      "updateTime": "2022-04-17T15:13:12.284Z",
      "_hasReleaseinfo": false,
      "_isExpand": false
    },
    {
      "id": 31971830,
      "country": "cn",
      "trackId": 481623196,
      "versionId": "336892925",
      "versionName": "4.1.1",
      "versionDate": null,
      "versionDescription": "",
      "createTime": "2022-04-17T15:13:12.284Z",
      "updateTime": "2022-04-17T15:13:12.284Z",
      "_hasReleaseinfo": false,
      "_isExpand": false
    },
    {
      "id": 31971831,
      "country": "cn",
      "trackId": 481623196,
      "versionId": "312673377",
      "versionName": "4.1",
      "versionDate": null,
      "versionDescription": "",
      "createTime": "2022-04-17T15:13:12.284Z",
      "updateTime": "2022-04-17T15:13:12.284Z",
      "_hasReleaseinfo": false,
      "_isExpand": false
    },
    {
      "id": 31971832,
      "country": "cn",
      "trackId": 481623196,
      "versionId": "244682880",
      "versionName": "4.0.1",
      "versionDate": null,
      "versionDescription": "",
      "createTime": "2022-04-17T15:13:12.284Z",
      "updateTime": "2022-04-17T15:13:12.284Z",
      "_hasReleaseinfo": false,
      "_isExpand": false
    },
    {
      "id": 31971833,
      "country": "cn",
      "trackId": 481623196,
      "versionId": "228612640",
      "versionName": "4.0",
      "versionDate": null,
      "versionDescription": "",
      "createTime": "2022-04-17T15:13:12.284Z",
      "updateTime": "2022-04-17T15:13:12.284Z",
      "_hasReleaseinfo": false,
      "_isExpand": false
    },
    {
      "id": 31971834,
      "country": "cn",
      "trackId": 481623196,
      "versionId": "15499690",
      "versionName": "3.1",
      "versionDate": null,
      "versionDescription": "",
      "createTime": "2022-04-17T15:13:12.284Z",
      "updateTime": "2022-04-17T15:13:12.284Z",
      "_hasReleaseinfo": false,
      "_isExpand": false
    }
  ]
}
